Workbook

Sheet Contents
A1: Sheet | B1: Contents
A2: HOW TO READ THIS WORKBOOK
A3: Inputs | B3: Every parameter in one cell. Change one and the workbook recalculates
A4: Assumptions | B4: Every judgment call, its status, and what needs State confirmation
A5: Variables | B5: Every column defined: formula, input data, source, code location
A6: DOCTORS
A7: Projection | B7: Main annual series 2011-2050, status quo. Live formulas throughout
A8: Scenarios | B8: The three scenarios compared at 2025, 2030, 2040, 2050
A9: Seats | B9: Government and private MBBS seats, and PG seats, by scenario
A10: Entrants | B10: Annual additions to the medical register, by origin
A11: Exits | B11: Retirements, deaths and migration, each year
A12: Specialists | B12: PG output and the active specialist stock
A13: Sensitivity | B13: Emigration rate; international density benchmarks
A14: Age sensitivity | B14: Age at registration varied from 22 to 26
A15: Validation | B15: Three checks, each labelled by how independent it actually is
A16: OTHER CADRES
A17: Cadre parameters | B17: Course length, fill rate, completion rate and its basis
A18: Cadre seats | B18: Sanctioned seats by cadre and year, the input to the formulas
A19: Cadre output | B19: Annual qualified output, twenty cadres, all live formulas
A20: Cadre by group | B20: The same totalled into six groups, with chart
A21: Nursing | B21: Nursing cadres in detail, with chart
A22: Data quality | B22: Pass-out years excluded as partial extracts
A23: Not covered | B23: Cadres absent or unusable, and the reason in each case
A24: ALL CADRES
A25: Total output | B25: Annual qualified output across every cadre including medical
A26: REFERENCE
A27: Parameters | B27: Every parameter, its value, and its source
A28: Specialities | B28: The specialist stock divided by discipline, with the observed registration shares and the women share
A29: Methodology | B29: Method in full, module by module
A30: Provenance | B30: Every figure classified: taken directly, estimated, derived, or assumed
A31: Data Sources | B31: Every source used, with publisher, coverage and link

Sheet Variables
A1: Variable | B1: What it is | C1: How it is computed | D1: Input data | E1: Source and code location
A2: Year | B2: Projection horizon, 2011 to 2050. 2011 is the base year of the official population series; 2025 is the last observed year. | C2: n/a | D2: n/a | E2: tn_supply_model.py line 42
A3: Basis | B3: Flag: Observed to 2025, Projected from 2026. Replaces shading so the workbook stays monochrome. | C3: Observed if Year <= 2025 | D3: n/a | E3: build_excel.py, basis()
A4: Population | B4: Tamil Nadu total population. The denominator for every density figure and for WHO need. | C4: 2011-2025: official NCP values used verbatim. 2026-2050: Pop(t) = Pop(t-1) x (1 + g), where g is the NCP series' own 2021 to 2025 average annual rate, 0.298 per cent, held constant (Inputs B28). | D4: NCP published table, 15 annual values to 2025 | E4: National Commission on Population, Ministry of Health and Family Welfare. Population Projections for India and States 2011-2036: Report of the Technical Group on Population Projections. New Delhi: Government of India; July 2019. The NCP series itself plateaus near 78 million from 2031; holding its recent rate instead is our choice so that the WHO requirement keeps rising with the population. Code: build_population()
A5: Government MBBS seats | B5: Sanctioned MBBS seats in government colleges, state selection-committee basis. | C5: To 2025: observed, used as given. From 2026: a POLICY SCENARIO, not an extrapolation, because government sets these seats. Three paths ramp from 5,200 to a target and then hold: frozen at 5,200 (no action at all); 6,000 by 2035 (the sixteen 100-seat colleges rise to 150); 9,250 by 2045 (all 37 colleges reach the NMC ceiling of 250, requiring no new college). Ramps round to NMC's 50-seat blocks. | D5: 11 annual observations 2015-16 to 2025-26, plus the 2025 college-level seat distribution | E5: TN Medical Selection Committee UG Data Sheet; MGRMU Seat Count Stat for the college-level distribution. Code: lines 95-135
A6: Private MBBS seats | B6: Sanctioned MBBS seats in self-financing colleges, same basis. | C6: To 2025: observed. From 2026: logistic S-curve, Seats(t) = K / (1 + exp(-r(t - t0))). K is the ceiling, set by scenario at 8,000 / 10,000 / 12,000; r and t0 are fitted by least squares in LEVELS to the 11 observed years. Fitted: K=10,000 gives r=0.204 and an inflection at 2025.5. | D6: 11 annual observations, 2015-16 to 2025-26 | E6: TN Medical Selection Committee, UG MBBS BDS Data Sheet. Code: lines 76-93, 120-130
A7: Total MBBS seats | B7: All sanctioned MBBS seats. | C7: Government MBBS seats + Private MBBS seats. No separate estimation. | D7: n/a | E7: Derived. Code: Projection sheet build, build_excel.py
A8: PG seats | B8: Sanctioned postgraduate medical seats (MD, MS and PG Diploma), full basis including deemed universities. | C8: 2021-2024: MGRMU seats scaled to full basis by 1.407. 2025-26: Selection Committee actual (5,534). From 2026: linear in levels, +321.5 seats/yr, then capped at 70% of Total MBBS seats. | D8: 5 annual observations, 2021 to 2025-26 | E8: MGRMU Seat Count Stat; TN Selection Committee MD and MS seat files. The 1.407 factor is validated: it reproduces 4,630 against the Committee's independent 4,629. Code: lines 135-155
A9: Entrants to register | B9: Doctors added to the Tamil Nadu medical register each year. The inflow to the stock. | C9: To 2025: observed registrations (TNMC MBBS + foreign medical graduates for 2020-2025; scraped register counts before that). From 2026: Domestic + External + FMG, where Domestic = Total MBBS seats six years earlier x 0.998 fill x 0.95 completion; External = 5,381 minus the deemed-overlap correction (806/yr from 2031); FMG = 1,606 + 170 per year, capped at 3,000. | D9: TNMC registrations 2020-2025; scraped register 1927-2019; seat series for the projected years | E9: TNMC Registrations workbook; NMC Indian Medical Register (scraped). Fill rate from MGRMU sanctioned-vs-admitted. Code: lines 160-210, 264-289
A10: Total exits | B10: Doctors leaving active practice each year, measured in active-practice equivalents, not raw headcount. | C10: Retirements + Deaths + Migration, each weighted by participation at the new age. Deaths = sum over cohorts of n x mortality(age) x participation(age). Migration = n x (1-mortality) x emigration(age) x participation(age). Retirements = n x [participation(age-1) - participation(age)]. The participation weighting is what makes exits reconcile exactly with the stock. | D10: Register cohorts by year of registration; age-banded mortality; calibrated emigration; a retirement participation curve | E10: Cohorts from the scraped register. Mortality from SRS-type age patterns adjusted for the professional class. Emigration is CALIBRATED at 1.2%/yr for ages 25-45, not observed. Code: lines 233-262, 295-328
A11: Net change | B11: Year-on-year change in the active doctor stock. | C11: Entrants to register - Total exits. This equals the actual change in Active doctors exactly, verified to under 1 doctor in all 39 year-transitions. | D11: n/a | E11: Derived. Identity checked in the counting audit
A12: Active doctors | B12: Doctors alive, resident in Tamil Nadu, and still in active practice. NOT the same as cumulative registrations. | C12: Register cohorts rolled forward from 1927. Each year every cohort is reduced by mortality and emigration, then multiplied by a participation factor set by its age. Active = sum over cohorts of surviving headcount x participation(age). Age is inferred as 24 at registration plus years elapsed. | D12: 193,264 scraped registrations by year, 1927-2025, with 2020-2025 taken on the TNMC basis | E12: NMC Indian Medical Register (scraped) and TNMC Registrations workbook. Age is INFERRED, not observed. Code: lines 212-292
... A18: Surplus vs revised need | B18: How far supply runs above the revised projected need. | C18: Active doctors - revised projected need. | D18: n/a | E18: Derived

Sheet Inputs
A1: Parameter | B1: Value | C1: Unit | D1: Basis and source
A2: WHO skilled health worker density norm | B2: 44.5 | C2: per 10,000 population | D2: WHO, Global Strategy on HRH: Workforce 2030 (2016)
A3: WHO doctor share of that norm | B3: 0.25 | C3: share | D3: WHO (2016), doctor to nurse ratio 1 to 3
A4: MBBS fill rate | B4: 0.998 | C4: share of sanctioned seats | D4: OBSERVED. MGRMU sanctioned against admitted, 2021-2025
A5: PG fill rate | B5: 0.978 | C5: share of sanctioned seats | D5: OBSERVED. MGRMU PG Medical sheet, 2021-2024
A6: Completion rate | B6: 0.95 | C6: share of admissions | D6: NMC benchmark. Validated: PG predicted 2,707 against 2,717 observed
A7: MBBS course lag | B7: 6 | C7: years | D7: 4.5 academic years plus 12-month internship, registration on completion
A8: PG course lag | B8: 3 | C8: years | D8: MD, MS, DM, M.Ch, DNB broad duration
A9: External entrants, flat | B9: 5381.0475 | C9: per year | D9: OBSERVED RESIDUAL. Registrations minus modelled domestic output, 2021-2025 mean
A10: Seat-source gap, 2025-26 and later | B10: 850 | C10: seats | D10: OBSERVED. Selection Committee 4,750 against MGRMU 3,900 for 2025-26
A11: Seat-source gap, seat year 2023 | B11: 450 | C11: seats | D11: OBSERVED. SC 3,850 against MGRMU 3,400
A12: Seat-source gap, seat year 2024 | B12: 550 | C12: seats | D12: OBSERVED. SC 4,050 against MGRMU 3,500
A13: Deemed overlap removed from residual | B13: =B10*B4*B6 | C13: graduates per year | D13: DERIVED, see formula in cell B13: gap x fill x completion
A14: Deemed overlap first full year | B14: 2031 | C14: year | D14: Seat year 2025 plus the 6-year MBBS lag
A15: Foreign medical graduates, 2025 base | B15: 1606 | C15: per year | D15: OBSERVED. TNMC registrations 2025
A16: Foreign medical graduates, annual increment | B16: 170 | C16: per year | D16: OBSERVED TREND. TNMC 2020-2025, fitted in levels
A17: Foreign medical graduates, ceiling | B17: 3000 | C17: per year | D17: ASSUMPTION. Roughly double the 2025 level, capped as domestic capacity expands
A18: Private MBBS ceiling K, status quo | B18: 10000 | C18: seats | D18: EXPERT-JUDGMENT SCENARIO BOUND, not a derived figure. See Assumptions sheet
A19: Private MBBS logistic growth r | B19: 0.204 | C19: per year | D19: FITTED by least squares in levels to 11 observed years, given K
A20: Private MBBS logistic midpoint t0 | B20: 10.5 | C20: years after 2015 | D20: FITTED with r. Inflection year = 2015 + t0
A21: Government MBBS 2025 level | B21: 5200 | C21: seats | D21: OBSERVED. Selection Committee 2025-26
A22: Government MBBS target, status quo | B22: 6000 | C22: seats | D22: POLICY SCENARIO. The sixteen 100-seat colleges rise to 150
A23: Government MBBS target year, status quo | B23: 2035 | C23: year | D23: POLICY SCENARIO. Pending confirmation with the State
A24: PG seats linear intercept | B24: 3953.4 | C24: seats at 2021 | D24: FITTED in levels to the 2021-2025 full-basis series
A25: PG seats linear slope | B25: 321.5 | C25: seats per year | D25: FITTED with the intercept
... A27: PG external entrants, flat | B27: 1598.6773 | C27: per year | D27: OBSERVED RESIDUAL. TNMC PG registrations minus seat-driven output, 2024-2025
A28: Population growth rate beyond 2025 | B28: =(Projection!C16/Projection!C12)^(1/4)-1 | C28: per year | D28: DERIVED, see formula in cell B28: NCP 2021 to 2025 average annual rate, held constant from 2026. The NCP series itself plateaus from 2031
A29: Population, last NCP year used verbatim | B29: 2025 | C29: year | D29: The model's last observed year. NCP tail growth for reference: -0.0038% per year at 2036
A30: Emigration and out-of-state loss | B30: 0.012 | C30: per year, ages 25-45 | D30: CALIBRATED, not observed. See Sensitivity sheet
A31: Age at registration | B31: 24 | C31: years | D31: INFERRED, not observed. See Age sensitivity sheet
A32: Revised need: income elasticity | B32: 0.244 | C32: elasticity | D32: PUBLISHED. Sum of the three GDP per capita lags in Table 1, 0.231 + 0.531 - 0.518, of Liu JX, Goryakin Y, Maeda A, Bruckner T, Scheffler RM. Global Health Workforce Labor Market Projections for 2030. Human Resources for Health. 2017;15:11. doi:10.1186/s12960-017-0187-2. First issued as World Bank Policy Research Working Paper 7790, Washington DC: World Bank; 2016.
A33: Revised need: out-of-pocket elasticity | B33: -0.099 | C33: elasticity | D33: PUBLISHED. Table 1 of Liu et al. 2017 (full reference in row 32)
A34: Revised need: population 65+ elasticity | B34: 0.516 | C34: elasticity | D34: PUBLISHED. Table 1 of Liu et al. 2017 (full reference in row 32)
A35: Revised need: real GSDP per capita growth, 2026 | B35: 0.065 | C35: per year | D35: ASSUMED, FOR STATE CONFIRMATION. Recent Tamil Nadu real GSDP growth less population growth. See Assumptions sheet
A36: Revised need: real GSDP per capita growth, 2050 | B36: 0.04 | C36: per year | D36: ASSUMED, FOR STATE CONFIRMATION. The 2026 rate eases linearly to this by 2050
A37: Revised need: OOP growth less GDP growth | B37: 0 | C37: per year | D37: ASSUMED. Zero holds the out-of-pocket share of spending constant
A38: Revised need: growth of population aged 65+ | B38: 0.035 | C38: per year | D38: ASSUMED, FOR STATE CONFIRMATION. To be replaced by the NCP 2019 age tables for Tamil Nadu

Sheet Projection
A1: Year | B1: Basis | C1: Population | D1: Government MBBS seats | E1: Private MBBS seats | F1: Total MBBS seats | G1: PG seats | H1: Domestic MBBS output | I1: External entrants | J1: Foreign medical graduates | K1: Entrants to register | L1: Retirements | M1: Deaths | N1: Migration | O1: Total exits | P1: Net change | Q1: Active doctors | R1: Doctors per 10,000 | S1: PG qualified output | T1: Specialist exits | U1: Active specialists | V1: WHO need (doctors) | W1: Surplus vs WHO need | X1: Revised projected need (doctors) | Y1: Surplus vs revised need
A2: 2011 | B2: Observed | C2: 72147000 | K2: 3473 | L2: 443.04516 | M2: 207.32089 | N2: 484.97764 | O2: =SUM(L2:N2) | P2: =K2-O2 | Q2: 63183.543 | R2: =Q2/C2*10000 | S2: 2091.871 | T2: 285.08184 | U2: 23373.226 | V2: =C2*Inputs!$B$2*Inputs!$B$3/10000 | W2: =Q2-V2
A3: 2012 | B3: Observed | C3: 72645000 | K3: 4183 | L3: 422.63452 | M3: 216.3532 | N3: 504.90209 | O3: =SUM(L3:N3) | P3: =K3-O3 | Q3: =Q2+P3 | R3: =Q3/C3*10000 | S3: 2091.871 | T3: 309.44097 | U3: =U2+S3-T3 | V3: =C3*Inputs!$B$2*Inputs!$B$3/10000 | W3: =Q3-V3
A4: 2013 | B4: Observed | C4: 73142000 | K4: 4623 | L4: 512.52115 | M4: 225.09288 | N4: 533.494 | O4: =SUM(L4:N4) | P4: =K4-O4 | Q4: =Q3+P4 | R4: =Q4/C4*10000 | S4: 2091.871 | T4: 333.47169 | U4: =U3+S4-T4 | V4: =C4*Inputs!$B$2*Inputs!$B$3/10000 | W4: =Q4-V4
A5: 2014 | B5: Observed | C5: 73640000 | K5: 5066 | L5: 597.26544 | M5: 235.07772 | N5: 565.32534 | O5: =SUM(L5:N5) | P5: =K5-O5 | Q5: =Q4+P5 | R5: =Q5/C5*10000 | S5: 2091.871 | T5: 357.17843 | U5: =U4+S5-T5 | V5: =C5*Inputs!$B$2*Inputs!$B$3/10000 | W5: =Q5-V5
A6: 2015 | B6: Observed | C6: 74137000 | D6: 2655 | E6: 1010 | F6: =D6+E6 | K6: 5091 | L6: 601.47699 | M6: 244.37376 | N6: 602.27992 | O6: =SUM(L6:N6) | P6: =K6-O6 | Q6: =Q5+P6 | R6: =Q6/C6*10000 | S6: 2091.871 | T6: 383.99331 | U6: =U5+S6-T6 | V6: =C6*Inputs!$B$2*Inputs!$B$3/10000 | W6: =Q6-V6
A7: 2016 | B7: Observed | C7: 74635000 | D7: 2650 | E7: 1610 | F7: =D7+E7 | K7: 6494 | L7: 610.25401 | M7: 252.71971 | N7: 641.09668 | O7: =SUM(L7:N7) | P7: =K7-O7 | Q7: =Q6+P7 | R7: =Q7/C7*10000 | S7: 2091.871 | T7: 389.97088 | U7: =U6+S7-T7 | V7: =C7*Inputs!$B$2*Inputs!$B$3/10000 | W7: =Q7-V7
A8: 2017 | B8: Observed | C8: 74989000 | D8: 3050 | E8: 1600 | F8: =D8+E8 | K8: 6961 | L8: 581.60723 | M8: 264.42009 | N8: 695.77075 | O8: =SUM(L8:N8) | P8: =K8-O8 | Q8: =Q7+P8 | R8: =Q8/C8*10000 | S8: 2091.871 | T8: 395.92753 | U8: =U7+S8-T8 | V8: =C8*Inputs!$B$2*Inputs!$B$3/10000 | W8: =Q8-V8
A9: 2018 | B9: Observed | C9: 75342000 | D9: 2900 | E9: 1600 | F9: =D9+E9 | K9: 7164 | L9: 648.47619 | M9: 275.32034 | N9: 753.94728 | O9: =SUM(L9:N9) | P9: =K9-O9 | Q9: =Q8+P9 | R9: =Q9/C9*10000 | S9: 2440.5161 | T9: 401.86333 | U9: =U8+S9-T9 | V9: =C9*Inputs!$B$2*Inputs!$B$3/10000 | W9: =Q9-V9
A10: 2019 | B10: Observed | C10: 75695000 | D10: 3600 | E10: 1950 | F10: =D10+E10 | K10: 8767 | L10: 727.28869 | M10: 284.66724 | N10: 810.62963 | O10: =SUM(L10:N10) | P10: =K10-O10 | Q10: =Q9+P10 | R10: =Q10/C10*10000 | S10: 2614.8387 | T10: 412.23767 | U10: =U9+S10-T10 | V10: =C10*Inputs!$B$2*Inputs!$B$3/10000 | W10: =Q10-V10
A11: 2020 | B11: Observed | C11: 76049000 | D11: 3675 | E11: 2350 | F11: =D11+E11 | J11: 640 | K11: 9049 | L11: 705.64101 | M11: 295.8177 | N11: 887.04056 | O11: =SUM(L11:N11) | P11: =K11-O11 | Q11: =Q10+P11 | R11: =Q11/C11*10000 | S11: 2702 | T11: 424.76392 | U11: =U10+S11-T11 | V11: =C11*Inputs!$B$2*Inputs!$B$3/10000 | W11: =Q11-V11
A12: 2021 | B12: Observed | C12: 76402000 | D12: 5175 | E12: 2900 | F12: =D12+E12 | G12: 4100 | H12: =F6*Inputs!$B$4*Inputs!$B$6 | I12: 4583.2135 | J12: 1268 | K12: =H12+I12+J12 | L12: 715.04956 | M12: 308.22106 | N12: 965.13076 | O12: =SUM(L12:N12) | P12: =K12-O12 | Q12: =Q11+P12 | R12: =Q12/C12*10000 | S12: 4210 | T12: 438.29955 | U12: =U11+S12-T12 | V12: =C12*Inputs!$B$2*Inputs!$B$3/10000 | W12: =Q12-V12
A13: 2022 | B13: Observed | C13: 76631000 | D13: 5175 | E13: 3350 | F13: =D13+E13 | G13: 4283 | H13: =F7*Inputs!$B$4*Inputs!$B$6 | I13: 6328.094 | J13: 1287 | K13: =H13+I13+J13 | L13: 758.52392 | M13: 321.01014 | N13: 1045.7949 | O13: =SUM(L13:N13) | P13: =K13-O13 | Q13: =Q12+P13 | R13: =Q13/C13*10000 | S13: 5632 | T13: 471.00454 | U13: =U12+S13-T13 | V13: =C13*Inputs!$B$2*Inputs!$B$3/10000 | W13: =Q13-V13
A14: 2023 | B14: Observed | C14: 76860000 | D14: 5200 | E14: 3850 | F14: =D14+E14 | G14: 4435 | H14: =F8*Inputs!$B$4*Inputs!$B$6 | I14: 4961.335 | J14: 1622 | K14: =H14+I14+J14 | L14: 740.56846 | M14: 335.44481 | N14: 1152.7074 | O14: =SUM(L14:N14) | P14: =K14-O14 | Q14: =Q13+P14 | R14: =Q14/C14*10000 | S14: 5279 | T14: 521.76257 | U14: =U13+S14-T14 | V14: =C14*Inputs!$B$2*Inputs!$B$3/10000 | W14: =Q14-V14
A15: 2024 | B15: Observed | C15: 77089000 | D15: 5200 | E15: 4050 | F15: =D15+E15 | G15: 4630 | H15: =F9*Inputs!$B$4*Inputs!$B$6 | I15: 5455.55 | J15: 1427 | K15: =H15+I15+J15 | L15: 774.66931 | M15: 348.91196 | N15: 1248.9461 | O15: =SUM(L15:N15) | P15: =K15-O15 | Q15: =Q14+P15 | R15: =Q15/C15*10000 | S15: 2917 | T15: 567.52199 | U15: =U14+S15-T15 | V15: =C15*Inputs!$B$2*Inputs!$B$3/10000 | W15: =Q15-V15
A16: 2025 | B16: Observed | C16: 77317000 | D16: 5200 | E16: 4750 | F16: =D16+E16 | G16: 5534 | H16: =F10*Inputs!$B$4*Inputs!$B$6 | I16: 5577.045 | J16: 1606 | K16: =H16+I16+J16 | L16: 781.78858 | M16: 362.0362 | N16: 1345.067 | O16: =SUM(L16:N16) | P16: =K16-O16 | Q16: =Q15+P16 | R16: =Q16/C16*10000 | S16: 8069 | T16: 591.69341 | U16: =U15+S16-T16 | V16: =C16*Inputs!$B$2*Inputs!$B$3/10000 | W16: =Q16-V16 | X16: =Q16 | Y16: =Q16-X16
A17: 2026 | B17: Projected | C17: =C16*(1+Inputs!$B$28) | D17: =IF(A17>=Inputs!$B$23,Inputs!$B$22,ROUND((Inputs!$B$21+(Inputs!$B$22-Inputs!$B$21)*(A17-2025)/(Inputs!$B$23-2025))/50,0)*50) | E17: =Inputs!$B$18/(1+EXP(-Inputs!$B$19*(A17-2015-Inputs!$B$20))) | F17: =D17+E17 | G17: =MIN(Inputs!$B$24+Inputs!$B$25*(A17-2021),Inputs!$B$26*F17) | H17: =F11*Inputs!$B$4*Inputs!$B$6 | I17: =Inputs!$B$9-IF(A17<2029,0,IF(A17=2029,Inputs!$B$11*Inputs!$B$4*Inputs!$B$6,IF(A17=2030,Inputs!$B$12*Inputs!$B$4*Inputs!$B$6,Inputs!$B$13))) | J17: =MIN(Inputs!$B$17,Inputs!$B$15+Inputs!$B$16*(A17-2025)) | K17: =H17+I17+J17 | L17: 794.22678 | M17: 374.77036 | N17: 1456.4786 | O17: =SUM(L17:N17) | P17: =K17-O17 | Q17: =Q16+P17 | R17: =Q17/C17*10000 | S17: =G14*Inputs!$B$5*Inputs!$B$6+Inputs!$B$27 | T17: 682.49355 | U17: =U16+S17-T17 | V17: =C17*Inputs!$B$2*Inputs!$B$3/10000 | W17: =Q17-V17 | X17: =X16/C16*C17*(1+(Inputs!$B$35+(Inputs!$B$36-Inputs!$B$35)*(A17-2026)/24))^Inputs!$B$32*(1+(Inputs!$B$35+(Inputs!$B$36-Inputs!$B$35)*(A17-2026)/24)+Inputs!$B$37)^Inputs!$B$33*(1+Inputs!$B$38)^Inputs!$B$34 | Y17: =Q17-X17
A18: 2027 | B18: Projected | C18: =C17*(1+Inputs!$B$28) | D18: =IF(A18>=Inputs!$B$23,Inputs!$B$22,ROUND((Inputs!$B$21+(Inputs!$B$22-Inputs!$B$21)*(A18-2025)/(Inputs!$B$23-2025))/50,0)*50) | E18: =Inputs!$B$18/(1+EXP(-Inputs!$B$19*(A18-2015-Inputs!$B$20))) | F18: =D18+E18 | G18: =MIN(Inputs!$B$24+Inputs!$B$25*(A18-2021),Inputs!$B$26*F18) | H18: =F12*Inputs!$B$4*Inputs!$B$6 | I18: =Inputs!$B$9-IF(A18<2029,0,IF(A18=2029,Inputs!$B$11*Inputs!$B$4*Inputs!$B$6,IF(A18=2030,Inputs!$B$12*Inputs!$B$4*Inputs!$B$6,Inputs!$B$13))) | J18: =MIN(Inputs!$B$17,Inputs!$B$15+Inputs!$B$16*(A18-2025)) | K18: =H18+I18+J18 | L18: 890.48864 | M18: 391.46694 | N18: 1573.4036 | O18: =SUM(L18:N18) | P18: =K18-O18 | Q18: =Q17+P18 | R18: =Q18/C18*10000 | S18: =G15*Inputs!$B$5*Inputs!$B$6+Inputs!$B$27 | T18: 743.04935 | U18: =U17+S18-T18 | V18: =C18*Inputs!$B$2*Inputs!$B$3/10000 | W18: =Q18-V18 | X18: =X17/C17*C18*(1+(Inputs!$B$35+(Inputs!$B$36-Inputs!$B$35)*(A18-2026)/24))^Inputs!$B$32*(1+(Inputs!$B$35+(Inputs!$B$36-Inputs!$B$35)*(A18-2026)/24)+Inputs!$B$37)^Inputs!$B$33*(1+Inputs!$B$38)^Inputs!$B$34 | Y18: =Q18-X18
A19: 2028 | B19: Projected | C19: =C18*(1+Inputs!$B$28) | D19: =IF(A19>=Inputs!$B$23,Inputs!$B$22,ROUND((Inputs!$B$21+(Inputs!$B$22-Inputs!$B$21)*(A19-2025)/(Inputs!$B$23-2025))/50,0)*50) | E19: =Inputs!$B$18/(1+EXP(-Inputs!$B$19*(A19-2015-Inputs!$B$20))) | F19: =D19+E19 | G19: =MIN(Inputs!$B$24+Inputs!$B$25*(A19-2021),Inputs!$B$26*F19) | H19: =F13*Inputs!$B$4*Inputs!$B$6 | I19: =Inputs!$B$9-IF(A19<2029,0,IF(A19=2029,Inputs!$B$11*Inputs!$B$4*Inputs!$B$6,IF(A19=2030,Inputs!$B$12*Inputs!$B$4*Inputs!$B$6,Inputs!$B$13))) | J19: =MIN(Inputs!$B$17,Inputs!$B$15+Inputs!$B$16*(A19-2025)) | K19: =H19+I19+J19 | L19: 826.96478 | M19: 410.26383 | N19: 1712.5789 | O19: =SUM(L19:N19) | P19: =K19-O19 | Q19: =Q18+P19 | R19: =Q19/C19*10000 | S19: =G16*Inputs!$B$5*Inputs!$B$6+Inputs!$B$27 | T19: 804.94055 | U19: =U18+S19-T19 | V19: =C19*Inputs!$B$2*Inputs!$B$3/10000 | W19: =Q19-V19 | X19: =X18/C18*C19*(1+(Inputs!$B$35+(Inputs!$B$36-Inputs!$B$35)*(A19-2026)/24))^Inputs!$B$32*(1+(Inputs!$B$35+(Inputs!$B$36-Inputs!$B$35)*(A19-2026)/24)+Inputs!$B$37)^Inputs!$B$33*(1+Inputs!$B$38)^Inputs!$B$34 | Y19: =Q19-X19
A20: 2029 | B20: Projected | C20: =C19*(1+Inputs!$B$28) | D20: =IF(A20>=Inputs!$B$23,Inputs!$B$22,ROUND((Inputs!$B$21+(Inputs!$B$22-Inputs!$B$21)*(A20-2025)/(Inputs!$B$23-2025))/50,0)*50) | E20: =Inputs!$B$18/(1+EXP(-Inputs!$B$19*(A20-2015-Inputs!$B$20))) | F20: =D20+E20 | G20: =MIN(Inputs!$B$24+Inputs!$B$25*(A20-2021),Inputs!$B$26*F20) | H20: =F14*Inputs!$B$4*Inputs!$B$6 | I20: =Inputs!$B$9-IF(A20<2029,0,IF(A20=2029,Inputs!$B$11*Inputs!$B$4*Inputs!$B$6,IF(A20=2030,Inputs!$B$12*Inputs!$B$4*Inputs!$B$6,Inputs!$B$13))) | J20: =MIN(Inputs!$B$17,Inputs!$B$15+Inputs!$B$16*(A20-2025)) | K20: =H20+I20+J20 | L20: 826.7016 | M20: 428.98463 | N20: 1854.5133 | O20: =SUM(L20:N20) | P20: =K20-O20 | Q20: =Q19+P20 | R20: =Q20/C20*10000 | S20: =G17*Inputs!$B$5*Inputs!$B$6+Inputs!$B$27 | T20: 875.25886 | U20: =U19+S20-T20 | V20: =C20*Inputs!$B$2*Inputs!$B$3/10000 | W20: =Q20-V20 | X20: =X19/C19*C20*(1+(Inputs!$B$35+(Inputs!$B$36-Inputs!$B$35)*(A20-2026)/24))^Inputs!$B$32*(1+(Inputs!$B$35+(Inputs!$B$36-Inputs!$B$35)*(A20-2026)/24)+Inputs!$B$37)^Inputs!$B$33*(1+Inputs!$B$38)^Inputs!$B$34 | Y20: =Q20-X20
A21: 2030 | B21: Projected | C21: =C20*(1+Inputs!$B$28) | D21: =IF(A21>=Inputs!$B$23,Inputs!$B$22,ROUND((Inputs!$B$21+(Inputs!$B$22-Inputs!$B$21)*(A21-2025)/(Inputs!$B$23-2025))/50,0)*50) | E21: =Inputs!$B$18/(1+EXP(-Inputs!$B$19*(A21-2015-Inputs!$B$20))) | F21: =D21+E21 | G21: =MIN(Inputs!$B$24+Inputs!$B$25*(A21-2021),Inputs!$B$26*F21) | H21: =F15*Inputs!$B$4*Inputs!$B$6 | I21: =Inputs!$B$9-IF(A21<2029,0,IF(A21=2029,Inputs!$B$11*Inputs!$B$4*Inputs!$B$6,IF(A21=2030,Inputs!$B$12*Inputs!$B$4*Inputs!$B$6,Inputs!$B$13))) | J21: =MIN(Inputs!$B$17,Inputs!$B$15+Inputs!$B$16*(A21-2025)) | K21: =H21+I21+J21 | L21: 844.4504 | M21: 450.22315 | N21: 1993.259 | O21: =SUM(L21:N21) | P21: =K21-O21 | Q21: =Q20+P21 | R21: =Q21/C21*10000 | S21: =G18*Inputs!$B$5*Inputs!$B$6+Inputs!$B$27 | T21: 1183.548 | U21: =U20+S21-T21 | V21: =C21*Inputs!$B$2*Inputs!$B$3/10000 | W21: =Q21-V21 | X21: =X20/C20*C21*(1+(Inputs!$B$35+(Inputs!$B$36-Inputs!$B$35)*(A21-2026)/24))^Inputs!$B$32*(1+(Inputs!$B$35+(Inputs!$B$36-Inputs!$B$35)*(A21-2026)/24)+Inputs!$B$37)^Inputs!$B$33*(1+Inputs!$B$38)^Inputs!$B$34 | Y21: =Q21-X21
A22: 2031 | B22: Projected | C22: =C21*(1+Inputs!$B$28) | D22: =IF(A22>=Inputs!$B$23,Inputs!$B$22,ROUND((Inputs!$B$21+(Inputs!$B$22-Inputs!$B$21)*(A22-2025)/(Inputs!$B$23-2025))/50,0)*50) | E22: =Inputs!$B$18/(1+EXP(-Inputs!$B$19*(A22-2015-Inputs!$B$20))) | F22: =D22+E22 | G22: =MIN(Inputs!$B$24+Inputs!$B$25*(A22-2021),Inputs!$B$26*F22) | H22: =F16*Inputs!$B$4*Inputs!$B$6 | I22: =Inputs!$B$9-IF(A22<2029,0,IF(A22=2029,Inputs!$B$11*Inputs!$B$4*Inputs!$B$6,IF(A22=2030,Inputs!$B$12*Inputs!$B$4*Inputs!$B$6,Inputs!$B$13))) | J22: =MIN(Inputs!$B$17,Inputs!$B$15+Inputs!$B$16*(A22-2025)) | K22: =H22+I22+J22 | L22: 853.96618 | M22: 472.63237 | N22: 2133.0474 | O22: =SUM(L22:N22) | P22: =K22-O22 | Q22: =Q21+P22 | R22: =Q22/C22*10000 | S22: =G19*Inputs!$B$5*Inputs!$B$6+Inputs!$B$27 | T22: 1255.9466 | U22: =U21+S22-T22 | V22: =C22*Inputs!$B$2*Inputs!$B$3/10000 | W22: =Q22-V22 | X22: =X21/C21*C22*(1+(Inputs!$B$35+(Inputs!$B$36-Inputs!$B$35)*(A22-2026)/24))^Inputs!$B$32*(1+(Inputs!$B$35+(Inputs!$B$36-Inputs!$B$35)*(A22-2026)/24)+Inputs!$B$37)^Inputs!$B$33*(1+Inputs!$B$38)^Inputs!$B$34 | Y22: =Q22-X22
A23: 2032 | B23: Projected | C23: =C22*(1+Inputs!$B$28) | D23: =IF(A23>=Inputs!$B$23,Inputs!$B$22,ROUND((Inputs!$B$21+(Inputs!$B$22-Inputs!$B$21)*(A23-2025)/(Inputs!$B$23-2025))/50,0)*50) | E23: =Inputs!$B$18/(1+EXP(-Inputs!$B$19*(A23-2015-Inputs!$B$20))) | F23: =D23+E23 | G23: =MIN(Inputs!$B$24+Inputs!$B$25*(A23-2021),Inputs!$B$26*F23) | H23: =F17*Inputs!$B$4*Inputs!$B$6 | I23: =Inputs!$B$9-IF(A23<2029,0,IF(A23=2029,Inputs!$B$11*Inputs!$B$4*Inputs!$B$6,IF(A23=2030,Inputs!$B$12*Inputs!$B$4*Inputs!$B$6,Inputs!$B$13))) | J23: =MIN(Inputs!$B$17,Inputs!$B$15+Inputs!$B$16*(A23-2025)) | K23: =H23+I23+J23 | L23: 975.5069 | M23: 493.28858 | N23: 2273.9841 | O23: =SUM(L23:N23) | P23: =K23-O23 | Q23: =Q22+P23 | R23: =Q23/C23*10000 | S23: =G20*Inputs!$B$5*Inputs!$B$6+Inputs!$B$27 | T23: 1331.3741 | U23: =U22+S23-T23 | V23: =C23*Inputs!$B$2*Inputs!$B$3/10000 | W23: =Q23-V23 | X23: =X22/C22*C23*(1+(Inputs!$B$35+(Inputs!$B$36-Inputs!$B$35)*(A23-2026)/24))^Inputs!$B$32*(1+(Inputs!$B$35+(Inputs!$B$36-Inputs!$B$35)*(A23-2026)/24)+Inputs!$B$37)^Inputs!$B$33*(1+Inputs!$B$38)^Inputs!$B$34 | Y23: =Q23-X23
A24: 2033 | B24: Projected | C24: =C23*(1+Inputs!$B$28) | D24: =IF(A24>=Inputs!$B$23,Inputs!$B$22,ROUND((Inputs!$B$21+(Inputs!$B$22-Inputs!$B$21)*(A24-2025)/(Inputs!$B$23-2025))/50,0)*50) | E24: =Inputs!$B$18/(1+EXP(-Inputs!$B$19*(A24-2015-Inputs!$B$20))) | F24: =D24+E24 | G24: =MIN(Inputs!$B$24+Inputs!$B$25*(A24-2021),Inputs!$B$26*F24) | H24: =F18*Inputs!$B$4*Inputs!$B$6 | I24: =Inputs!$B$9-IF(A24<2029,0,IF(A24=2029,Inputs!$B$11*Inputs!$B$4*Inputs!$B$6,IF(A24=2030,Inputs!$B$12*Inputs!$B$4*Inputs!$B$6,Inputs!$B$13))) | J24: =MIN(Inputs!$B$17,Inputs!$B$15+Inputs!$B$16*(A24-2025)) | K24: =H24+I24+J24 | L24: 951.26888 | M24: 519.28375 | N24: 2421.1728 | O24: =SUM(L24:N24) | P24: =K24-O24 | Q24: =Q23+P24 | R24: =Q24/C24*10000 | S24: =G21*Inputs!$B$5*Inputs!$B$6+Inputs!$B$27 | T24: 1410.7941 | U24: =U23+S24-T24 | V24: =C24*Inputs!$B$2*Inputs!$B$3/10000 | W24: =Q24-V24 | X24: =X23/C23*C24*(1+(Inputs!$B$35+(Inputs!$B$36-Inputs!$B$35)*(A24-2026)/24))^Inputs!$B$32*(1+(Inputs!$B$35+(Inputs!$B$36-Inputs!$B$35)*(A24-2026)/24)+Inputs!$B$37)^Inputs!$B$33*(1+Inputs!$B$38)^Inputs!$B$34 | Y24: =Q24-X24
A25: 2034 | B25: Projected | C25: =C24*(1+Inputs!$B$28) | D25: =IF(A25>=Inputs!$B$23,Inputs!$B$22,ROUND((Inputs!$B$21+(Inputs!$B$22-Inputs!$B$21)*(A25-2025)/(Inputs!$B$23-2025))/50,0)*50) | E25: =Inputs!$B$18/(1+EXP(-Inputs!$B$19*(A25-2015-Inputs!$B$20))) | F25: =D25+E25 | G25: =MIN(Inputs!$B$24+Inputs!$B$25*(A25-2021),Inputs!$B$26*F25) | H25: =F19*Inputs!$B$4*Inputs!$B$6 | I25: =Inputs!$B$9-IF(A25<2029,0,IF(A25=2029,Inputs!$B$11*Inputs!$B$4*Inputs!$B$6,IF(A25=2030,Inputs!$B$12*Inputs!$B$4*Inputs!$B$6,Inputs!$B$13))) | J25: =MIN(Inputs!$B$17,Inputs!$B$15+Inputs!$B$16*(A25-2025)) | K25: =H25+I25+J25 | L25: 923.99548 | M25: 546.34581 | N25: 2568.3297 | O25: =SUM(L25:N25) | P25: =K25-O25 | Q25: =Q24+P25 | R25: =Q25/C25*10000 | S25: =G22*Inputs!$B$5*Inputs!$B$6+Inputs!$B$27 | T25: 1489.9143 | U25: =U24+S25-T25 | V25: =C25*Inputs!$B$2*Inputs!$B$3/10000 | W25: =Q25-V25 | X25: =X24/C24*C25*(1+(Inputs!$B$35+(Inputs!$B$36-Inputs!$B$35)*(A25-2026)/24))^Inputs!$B$32*(1+(Inputs!$B$35+(Inputs!$B$36-Inputs!$B$35)*(A25-2026)/24)+Inputs!$B$37)^Inputs!$B$33*(1+Inputs!$B$38)^Inputs!$B$34 | Y25: =Q25-X25
A26: 2035 | B26: Projected | C26: =C25*(1+Inputs!$B$28) | D26: =IF(A26>=Inputs!$B$23,Inputs!$B$22,ROUND((Inputs!$B$21+(Inputs!$B$22-Inputs!$B$21)*(A26-2025)/(Inputs!$B$23-2025))/50,0)*50) | E26: =Inputs!$B$18/(1+EXP(-Inputs!$B$19*(A26-2015-Inputs!$B$20))) | F26: =D26+E26 | G26: =MIN(Inputs!$B$24+Inputs!$B$25*(A26-2021),Inputs!$B$26*F26) | H26: =F20*Inputs!$B$4*Inputs!$B$6 | I26: =Inputs!$B$9-IF(A26<2029,0,IF(A26=2029,Inputs!$B$11*Inputs!$B$4*Inputs!$B$6,IF(A26=2030,Inputs!$B$12*Inputs!$B$4*Inputs!$B$6,Inputs!$B$13))) | J26: =MIN(Inputs!$B$17,Inputs!$B$15+Inputs!$B$16*(A26-2025)) | K26: =H26+I26+J26 | L26: 946.06544 | M26: 571.96747 | N26: 2716.6673 | O26: =SUM(L26:N26) | P26: =K26-O26 | Q26: =Q25+P26 | R26: =Q26/C26*10000 | S26: =G23*Inputs!$B$5*Inputs!$B$6+Inputs!$B$27 | T26: 1956.8294 | U26: =U25+S26-T26 | V26: =C26*Inputs!$B$2*Inputs!$B$3/10000 | W26: =Q26-V26 | X26: =X25/C25*C26*(1+(Inputs!$B$35+(Inputs!$B$36-Inputs!$B$35)*(A26-2026)/24))^Inputs!$B$32*(1+(Inputs!$B$35+(Inputs!$B$36-Inputs!$B$35)*(A26-2026)/24)+Inputs!$B$37)^Inputs!$B$33*(1+Inputs!$B$38)^Inputs!$B$34 | Y26: =Q26-X26
A27: 2036 | B27: Projected | C27: =C26*(1+Inputs!$B$28) | D27: =IF(A27>=Inputs!$B$23,Inputs!$B$22,ROUND((Inputs!$B$21+(Inputs!$B$22-Inputs!$B$21)*(A27-2025)/(Inputs!$B$23-2025))/50,0)*50) | E27: =Inputs!$B$18/(1+EXP(-Inputs!$B$19*(A27-2015-Inputs!$B$20))) | F27: =D27+E27 | G27: =MIN(Inputs!$B$24+Inputs!$B$25*(A27-2021),Inputs!$B$26*F27) | H27: =F21*Inputs!$B$4*Inputs!$B$6 | I27: =Inputs!$B$9-IF(A27<2029,0,IF(A27=2029,Inputs!$B$11*Inputs!$B$4*Inputs!$B$6,IF(A27=2030,Inputs!$B$12*Inputs!$B$4*Inputs!$B$6,Inputs!$B$13))) | J27: =MIN(Inputs!$B$17,Inputs!$B$15+Inputs!$B$16*(A27-2025)) | K27: =H27+I27+J27 | L27: 958.94921 | M27: 597.39938 | N27: 2864.8939 | O27: =SUM(L27:N27) | P27: =K27-O27 | Q27: =Q26+P27 | R27: =Q27/C27*10000 | S27: =G24*Inputs!$B$5*Inputs!$B$6+Inputs!$B$27 | T27: 2050.0895 | U27: =U26+S27-T27 | V27: =C27*Inputs!$B$2*Inputs!$B$3/10000 | W27: =Q27-V27 | X27: =X26/C26*C27*(1+(Inputs!$B$35+(Inputs!$B$36-Inputs!$B$35)*(A27-2026)/24))^Inputs!$B$32*(1+(Inputs!$B$35+(Inputs!$B$36-Inputs!$B$35)*(A27-2026)/24)+Inputs!$B$37)^Inputs!$B$33*(1+Inputs!$B$38)^Inputs!$B$34 | Y27: =Q27-X27
A28: 2037 | B28: Projected | C28: =C27*(1+Inputs!$B$28) | D28: =IF(A28>=Inputs!$B$23,Inputs!$B$22,ROUND((Inputs!$B$21+(Inputs!$B$22-Inputs!$B$21)*(A28-2025)/(Inputs!$B$23-2025))/50,0)*50) | E28: =Inputs!$B$18/(1+EXP(-Inputs!$B$19*(A28-2015-Inputs!$B$20))) | F28: =D28+E28 | G28: =MIN(Inputs!$B$24+Inputs!$B$25*(A28-2021),Inputs!$B$26*F28) | H28: =F22*Inputs!$B$4*Inputs!$B$6 | I28: =Inputs!$B$9-IF(A28<2029,0,IF(A28=2029,Inputs!$B$11*Inputs!$B$4*Inputs!$B$6,IF(A28=2030,Inputs!$B$12*Inputs!$B$4*Inputs!$B$6,Inputs!$B$13))) | J28: =MIN(Inputs!$B$17,Inputs!$B$15+Inputs!$B$16*(A28-2025)) | K28: =H28+I28+J28 | L28: 1045.6525 | M28: 626.3404 | N28: 3016.9837 | O28: =SUM(L28:N28) | P28: =K28-O28 | Q28: =Q27+P28 | R28: =Q28/C28*10000 | S28: =G25*Inputs!$B$5*Inputs!$B$6+Inputs!$B$27 | T28: 2133.5399 | U28: =U27+S28-T28 | V28: =C28*Inputs!$B$2*Inputs!$B$3/10000 | W28: =Q28-V28 | X28: =X27/C27*C28*(1+(Inputs!$B$35+(Inputs!$B$36-Inputs!$B$35)*(A28-2026)/24))^Inputs!$B$32*(1+(Inputs!$B$35+(Inputs!$B$36-Inputs!$B$35)*(A28-2026)/24)+Inputs!$B$37)^Inputs!$B$33*(1+Inputs!$B$38)^Inputs!$B$34 | Y28: =Q28-X28
... A41: 2050 | B41: Projected | C41: =C40*(1+Inputs!$B$28) | D41: =IF(A41>=Inputs!$B$23,Inputs!$B$22,ROUND((Inputs!$B$21+(Inputs!$B$22-Inputs!$B$21)*(A41-2025)/(Inputs!$B$23-2025))/50,0)*50) | E41: =Inputs!$B$18/(1+EXP(-Inputs!$B$19*(A41-2015-Inputs!$B$20))) | F41: =D41+E41 | G41: =MIN(Inputs!$B$24+Inputs!$B$25*(A41-2021),Inputs!$B$26*F41) | H41: =F35*Inputs!$B$4*Inputs!$B$6 | I41: =Inputs!$B$9-IF(A41<2029,0,IF(A41=2029,Inputs!$B$11*Inputs!$B$4*Inputs!$B$6,IF(A41=2030,Inputs!$B$12*Inputs!$B$4*Inputs!$B$6,Inputs!$B$13))) | J41: =MIN(Inputs!$B$17,Inputs!$B$15+Inputs!$B$16*(A41-2025)) | K41: =H41+I41+J41 | L41: 1691.6943 | M41: 1254.6998 | N41: 4503.3566 | O41: =SUM(L41:N41) | P41: =K41-O41 | Q41: =Q40+P41 | R41: =Q41/C41*10000 | S41: =G38*Inputs!$B$5*Inputs!$B$6+Inputs!$B$27 | T41: 3934.5248 | U41: =U40+S41-T41 | V41: =C41*Inputs!$B$2*Inputs!$B$3/10000 | W41: =Q41-V41 | X41: =X40/C40*C41*(1+(Inputs!$B$35+(Inputs!$B$36-Inputs!$B$35)*(A41-2026)/24))^Inputs!$B$32*(1+(Inputs!$B$35+(Inputs!$B$36-Inputs!$B$35)*(A41-2026)/24)+Inputs!$B$37)^Inputs!$B$33*(1+Inputs!$B$38)^Inputs!$B$34 | Y41: =Q41-X41
A43: Every cell in columns F, H, K, O, P, Q, R, S, U, V, W, X and Y is a live formula. Change any parameter on the Inputs sheet and this sheet recalculates.
A44: Typed numbers appear only where a formula is not possible: published population (column C to 2025), observed seats and registrations to 2025,
A45: and the three cohort-model flows in columns L, M and N, which depend on the full age distribution of the register and cannot be written as a sheet formula.
A46: Active doctors in column Q is the running identity Q(t) = Q(t-1) + entrants - exits, which the model verifies to under one doctor in all 39 transitions.

Sheet Scenarios
A1: Scenario | B1: Metric | C1: 2025 | D1: 2030 | E1: 2040 | F1: 2050
A2: Constrained | B2: Government MBBS seats | C2: 5200 | D2: 5200 | E2: 5200 | F2: 5200
A3: Constrained | B3: Private MBBS seats | C3: 4750 | D3: 6503 | E3: 7812 | F3: 7980
A4: Constrained | B4: Total MBBS seats | C4: 9950 | D4: 11703 | E4: 13012 | F4: 13180
A5: Constrained | B5: PG seats | C5: 5534 | D5: 6847 | E5: 9109 | F5: 9226
A6: Constrained | B6: Entrants to register | C6: 12445 | D6: 16086 | E6: 19443 | F6: 20017
A7: Constrained | B7: Active doctors | C7: 151248 | D7: 211758 | E7: 351710 | F7: 488238
A8: Constrained | B8: Doctors per 10,000 | C8: 19.6 | D8: 27 | E8: 43.5 | F8: 58.6
A9: Constrained | B9: Active specialists | C9: 63790 | D9: 91690 | E9: 159757 | F9: 227848
A10: Status quo | B10: Government MBBS seats | C10: 5200 | D10: 5600 | E10: 6000 | F10: 6000
A11: Status quo | B11: Private MBBS seats | C11: 4750 | D11: 7146 | E11: 9506 | F11: 9933
A12: Status quo | B12: Total MBBS seats | C12: 9950 | D12: 12746 | E12: 15506 | F12: 15933
A13: Status quo | B13: PG seats | C13: 5534 | D13: 6847 | E13: 10062 | F13: 11153
... A25: Policy push | B25: Active specialists | C25: 63790 | D25: 91690 | E25: 159860 | F25: 243279
A27: Scenario | B27: Active doctors 2050
A28: Constrained | B28: 488238
A29: Status quo | B29: 517657
A30: Policy push | B30: 557109

Sheet Seats
A1: Year | B1: Basis | C1: Government MBBS (baseline) | D1: Government MBBS (policy push) | E1: Private MBBS (constrained) | F1: Private MBBS (status quo) | G1: Private MBBS (policy push) | H1: PG seats (status quo)
A2: 2011 | B2: Observed
A3: 2012 | B3: Observed
A4: 2013 | B4: Observed
A5: 2014 | B5: Observed
A6: 2015 | B6: Observed | C6: 2655 | D6: 2655 | E6: 1010 | F6: 1010 | G6: 1010
A7: 2016 | B7: Observed | C7: 2650 | D7: 2650 | E7: 1610 | F7: 1610 | G7: 1610
A8: 2017 | B8: Observed | C8: 3050 | D8: 3050 | E8: 1600 | F8: 1600 | G8: 1600
A9: 2018 | B9: Observed | C9: 2900 | D9: 2900 | E9: 1600 | F9: 1600 | G9: 1600
A10: 2019 | B10: Observed | C10: 3600 | D10: 3600 | E10: 1950 | F10: 1950 | G10: 1950
A11: 2020 | B11: Observed | C11: 3675 | D11: 3675 | E11: 2350 | F11: 2350 | G11: 2350
A12: 2021 | B12: Observed | C12: 5175 | D12: 5175 | E12: 2900 | F12: 2900 | G12: 2900 | H12: 4100
A13: 2022 | B13: Observed | C13: 5175 | D13: 5175 | E13: 3350 | F13: 3350 | G13: 3350 | H13: 4283
A14: 2023 | B14: Observed | C14: 5200 | D14: 5200 | E14: 3850 | F14: 3850 | G14: 3850 | H14: 4435
A15: 2024 | B15: Observed | C15: 5200 | D15: 5200 | E15: 4050 | F15: 4050 | G15: 4050 | H15: 4630
A16: 2025 | B16: Observed | C16: 5200 | D16: 5200 | E16: 4750 | F16: 4750 | G16: 4750 | H16: 5534
A17: 2026 | B17: Projected | C17: 5300 | D17: 5400 | E17: 5101 | F17: 5255 | G17: 5298 | H17: 5561
A18: 2027 | B18: Projected | C18: 5350 | D18: 5600 | E18: 5504 | F18: 5759 | G18: 5859 | H18: 5882
A19: 2028 | B19: Projected | C19: 5450 | D19: 5800 | E19: 5875 | F19: 6248 | G19: 6422 | H19: 6204
A20: 2029 | B20: Projected | C20: 5500 | D20: 6000 | E20: 6209 | F20: 6713 | G20: 6978 | H20: 6525
A21: 2030 | B21: Projected | C21: 5600 | D21: 6200 | E21: 6503 | F21: 7146 | G21: 7517 | H21: 6847
A22: 2031 | B22: Projected | C22: 5700 | D22: 6400 | E22: 6759 | F22: 7544 | G22: 8032 | H22: 7168
A23: 2032 | B23: Projected | C23: 5750 | D23: 6600 | E23: 6978 | F23: 7902 | G23: 8514 | H23: 7490
... A41: 2050 | B41: Projected | C41: 6000 | D41: 9250 | E41: 7980 | F41: 9933 | G41: 11836 | H41: 11153

Sheet Entrants
A1: Year | B1: Basis | C1: Tamil Nadu state-counselling graduates | D1: Deemed universities and out-of-state | E1: Foreign medical graduates | F1: Total entrants
A2: 2021 | B2: Observed | C2: 3475 | D2: 4583 | E2: 1268 | F2: 9326
A3: 2022 | B3: Observed | C3: 4039 | D3: 6328 | E3: 1287 | F3: 11654
A4: 2023 | B4: Observed | C4: 4409 | D4: 4961 | E4: 1622 | F4: 10992
A5: 2024 | B5: Observed | C5: 4266 | D5: 5456 | E5: 1427 | F5: 11149
A6: 2025 | B6: Observed | C6: 5262 | D6: 5577 | E6: 1606 | F6: 12445
A7: 2026 | B7: Projected | C7: 5712 | D7: 5381 | E7: 1776 | F7: 12869
A8: 2027 | B8: Projected | C8: 7656 | D8: 5381 | E8: 1946 | F8: 14983
A9: 2028 | B9: Projected | C9: 8083 | D9: 5381 | E9: 2116 | F9: 15580
A10: 2029 | B10: Projected | C10: 8580 | D10: 4954 | E10: 2286 | F10: 15821
A11: 2030 | B11: Projected | C11: 8770 | D11: 4860 | E11: 2456 | F11: 16086
A12: 2031 | B12: Projected | C12: 9434 | D12: 4575 | E12: 2626 | F12: 16635
A13: 2032 | B13: Projected | C13: 10007 | D13: 4575 | E13: 2796 | F13: 17378
... A31: 2050 | B31: Projected | C31: 14957 | D31: 4575 | E31: 3000 | F31: 22532

Sheet Exits
A1: Year | B1: Basis | C1: Retirements | D1: Deaths | E1: Migration and out-of-state | F1: Total exits | G1: Entrants | H1: Net change | I1: Exits as % of stock | J1: Entrants per exit
A2: 2015 | B2: Observed | C2: 601 | D2: 244 | E2: 602 | F2: 1448 | G2: 5091 | H2: 3643 | I2: 1.88 | J2: 3.5
A3: 2016 | B3: Observed | C3: 610 | D3: 253 | E3: 641 | F3: 1504 | G3: 6494 | H3: 4990 | I3: 1.84 | J3: 4.3
A4: 2017 | B4: Observed | C4: 582 | D4: 264 | E4: 696 | F4: 1542 | G4: 6961 | H4: 5419 | I4: 1.77 | J4: 4.5
A5: 2018 | B5: Observed | C5: 648 | D5: 275 | E5: 754 | F5: 1678 | G5: 7164 | H5: 5486 | I5: 1.81 | J5: 4.3
A6: 2019 | B6: Observed | C6: 727 | D6: 285 | E6: 811 | F6: 1823 | G6: 8767 | H6: 6944 | I6: 1.83 | J6: 4.8
A7: 2020 | B7: Observed | C7: 706 | D7: 296 | E7: 887 | F7: 1888 | G7: 9049 | H7: 7161 | I7: 1.77 | J7: 4.8
A8: 2021 | B8: Observed | C8: 715 | D8: 308 | E8: 965 | F8: 1988 | G8: 9326 | H8: 7338 | I8: 1.74 | J8: 4.7
A9: 2022 | B9: Observed | C9: 759 | D9: 321 | E9: 1046 | F9: 2125 | G9: 11654 | H9: 9529 | I9: 1.72 | J9: 5.5
A10: 2023 | B10: Observed | C10: 741 | D10: 335 | E10: 1153 | F10: 2229 | G10: 10992 | H10: 8763 | I10: 1.68 | J10: 4.9
A11: 2024 | B11: Observed | C11: 775 | D11: 349 | E11: 1249 | F11: 2373 | G11: 11149 | H11: 8776 | I11: 1.68 | J11: 4.7
A12: 2025 | B12: Observed | C12: 782 | D12: 362 | E12: 1345 | F12: 2489 | G12: 12445 | H12: 9956 | I12: 1.65 | J12: 5
A13: 2026 | B13: Projected | C13: 794 | D13: 375 | E13: 1456 | F13: 2625 | G13: 12869 | H13: 10244 | I13: 1.63 | J13: 4.9
... A37: 2050 | B37: Projected | C37: 1692 | D37: 1255 | E37: 4503 | F37: 7450 | G37: 22532 | H37: 15082 | I37: 1.44 | J37: 3
A39: Cumulative 2026-2050 | B39: Total | C39: Share of exits
A40: Retirements | B40: 27600 | C40: 0.22471832
A41: Deaths | B41: 17914 | C41: 0.1458506
A42: Migration and out-of-state | B42: 77307 | C42: 0.62943107
A43: Total exits | B43: 122821 | C43: 1
A44: Entrants | B44: 489230
A45: Net addition | B45: 366409

Sheet Specialists
A1: Year | B1: Basis | C1: PG seats | D1: PG graduates | E1: Active specialists | F1: Active doctors | G1: Specialist share
A2: 2011 | B2: Observed | D2: 2092 | E2: 23373 | F2: 63184 | G2: 0.3699
A3: 2012 | B3: Observed | D3: 2092 | E3: 25156 | F3: 66223 | G3: 0.3799
A4: 2013 | B4: Observed | D4: 2092 | E4: 26914 | F4: 69575 | G4: 0.3868
A5: 2014 | B5: Observed | D5: 2092 | E5: 28649 | F5: 73243 | G5: 0.3911
A6: 2015 | B6: Observed | D6: 2092 | E6: 30357 | F6: 76886 | G6: 0.3948
A7: 2016 | B7: Observed | D7: 2092 | E7: 32059 | F7: 81876 | G7: 0.3916
A8: 2017 | B8: Observed | D8: 2092 | E8: 33754 | F8: 87295 | G8: 0.3867
A9: 2018 | B9: Observed | D9: 2441 | E9: 35793 | F9: 92781 | G9: 0.3858
A10: 2019 | B10: Observed | D10: 2615 | E10: 37996 | F10: 99726 | G10: 0.381
A11: 2020 | B11: Observed | D11: 2702 | E11: 40273 | F11: 106886 | G11: 0.3768
A12: 2021 | B12: Observed | C12: 4100 | D12: 4210 | E12: 44045 | F12: 114224 | G12: 0.3856
A13: 2022 | B13: Observed | C13: 4283 | D13: 5632 | E13: 49206 | F13: 123752 | G13: 0.3976
A14: 2023 | B14: Observed | C14: 4435 | D14: 5279 | E14: 53963 | F14: 132516 | G14: 0.4072
A15: 2024 | B15: Observed | C15: 4630 | D15: 2917 | E15: 56312 | F15: 141292 | G15: 0.3986
A16: 2025 | B16: Observed | C16: 5534 | D16: 8069 | E16: 63790 | F16: 151248 | G16: 0.4218
A17: 2026 | B17: Projected | C17: 5561 | D17: 5719 | E17: 68826 | F17: 161492 | G17: 0.4262
A18: 2027 | B18: Projected | C18: 5882 | D18: 5900 | E18: 73984 | F18: 173620 | G18: 0.4261
A19: 2028 | B19: Projected | C19: 6204 | D19: 6740 | E19: 79919 | F19: 186249 | G19: 0.4291
A20: 2029 | B20: Projected | C20: 6525 | D20: 6765 | E20: 85809 | F20: 198960 | G20: 0.4313
A21: 2030 | B21: Projected | C21: 6847 | D21: 7064 | E21: 91690 | F21: 211758 | G21: 0.433
A22: 2031 | B22: Projected | C22: 7168 | D22: 7363 | E22: 97796 | F22: 224933 | G22: 0.4348
A23: 2032 | B23: Projected | C23: 7490 | D23: 7661 | E23: 104127 | F23: 238568 | G23: 0.4365
... A41: 2050 | B41: Projected | C41: 11153 | D41: 11925 | E41: 240513 | F41: 517657 | G41: 0.4646

Sheet Specialities
A1: Discipline | B1: Awards counted | C1: Registered 2020-2025 | D1: Share of PG output | E1: Women, observed | F1: Active specialists 2025 | G1: Active specialists 2040 | H1: Active specialists 2050 | I1: Qualifying per year 2050
A2: General Medicine | B2: DNB+MD | C2: 3788 | D2: 0.13149 | E2: 0.3506 | F2: 8387 | G2: 21019 | H2: 31624 | I2: 1568
A3: General Surgery | B3: DNB+MS | C3: 3504 | D3: 0.12163 | E3: 0.2774 | F3: 7759 | G3: 19444 | H3: 29253 | I3: 1450
A4: Anesthesiology | B4: DNB+MD | C4: 3090 | D4: 0.10726 | E4: 0.5362 | F4: 6842 | G4: 17146 | H4: 25797 | I4: 1279
A5: Obstetrics and Gynaecology | B5: DNB+MS | C5: 2662 | D5: 0.0924 | E5: 0.9707 | F5: 5894 | G5: 14771 | H5: 22224 | I5: 1102
A6: Paediatrics | B6: DNB+MD | C6: 2497 | D6: 0.08667 | E6: 0.5839 | F6: 5529 | G6: 13856 | H6: 20846 | I6: 1034
A7: Ophthalmology | B7: DNB+MS | C7: 1919 | D7: 0.06661 | E7: 0.7978 | F7: 4249 | G7: 10648 | H7: 16021 | I7: 794
A8: Orthopaedics | B8: DNB+MS | C8: 1864 | D8: 0.0647 | E8: 0.0311 | F8: 4127 | G8: 10343 | H8: 15562 | I8: 772
A9: Radiodiagnosis | B9: DNB+MD | C9: 1604 | D9: 0.05568 | E9: 0.4582 | F9: 3552 | G9: 8901 | H9: 13391 | I9: 664
A10: Pathology | B10: DNB+MD | C10: 1172 | D10: 0.04068 | E10: 0.8225 | F10: 2595 | G10: 6503 | H10: 9785 | I10: 485
A11: ENT (Otorhinolaryngology) | B11: DNB+MS | C11: 1029 | D11: 0.03572 | E11: 0.619 | F11: 2278 | G11: 5710 | H11: 8591 | I11: 426
A12: Dermatology, Venereology and Leprosy | B12: DNB+MD | C12: 905 | D12: 0.03141 | E12: 0.6884 | F12: 2004 | G12: 5022 | H12: 7555 | I12: 375
A13: Community Medicine | B13: DNB+MD | C13: 772 | D13: 0.0268 | E13: 0.557 | F13: 1709 | G13: 4284 | H13: 6445 | I13: 320
... A29: Medical Genetics | B29: DNB | C29: 1 | D29: 3e-05 | E29: 1 | F29: 2 | G29: 6 | H29: 8 | I29: 0
A30: TOTAL | C30: 28809 | D30: 1 | F30: 63790 | G30: 159860 | H30: 240513 | I30: 11925
A32: Observed registrations by speciality, Tamil Nadu Medical Council, 2020 to 2025: MD, MS, DNB medical broad speciality and DNB surgical broad speciality.
A33: These four streams sum to the PG registrations used in the Projection sheet in all six years, so the shares divide the specialist stock without changing it.
A34: Superspecialty (DM, M.Ch, DNB superspeciality) and PG Diploma are outside this total, as they are outside the specialist account, to avoid double counting.
A35: Each discipline is assumed to hold its observed share of PG output. This is a split of an aggregate, not a projection per discipline.
A36: The women column is observed, not modelled.

Sheet Sensitivity
A1: Emigration rate, ages 25-45 | B1: Cumulative loss over 21 years | C1: Active doctors 2025 | D1: Active doctors 2050 | E1: Doctors per 10,000 in 2050 | F1: Note
A2: 0.006 | B2: 0.11871968 | C2: 160210 | D2: 557686 | E2: 67
A3: 0.012 | B3: 0.22393904 | C3: 151248 | D3: 517657 | E3: 62.2 | F3: Central case
A4: 0.02 | B4: 0.34574419 | C4: 140448 | D4: 469842 | E4: 56.4
A5: 0.03 | B5: 0.47251949 | C5: 128570 | D5: 417894 | E5: 50.2
A7: Comparator | B7: Doctors per 10,000
A8: India, all states, active, approximate | B8: 7 to 9
A9: Tamil Nadu, modelled 2025 | B9: 19.6
A10: United Kingdom | B10: 32
A11: OECD average | B11: 35
A12: Tamil Nadu, modelled 2050, status quo | B12: 68.7
A13: Cuba, world's highest | B13: 84
A14: Note | B14: International figures are indicative orders of magnitude for context, not sourced point estimates.

Sheet Validation
A1: Check | B1: Year | C1: Model or scraped value | D1: Comparison value | E1: Difference | F1: Independence
A2: 1. Register cross-check | B2: 2020 | C2: 9049 | D2: 9049 | E2: 0 | F2: INDEPENDENT
A3: 1. Register cross-check | B3: 2021 | C3: 9326 | D3: 9326 | E3: 0 | F3: INDEPENDENT
A4: 1. Register cross-check | B4: 2022 | C4: 11654 | D4: 11654 | E4: 0 | F4: INDEPENDENT
A5: 1. Register cross-check | B5: 2023 | C5: 10992 | D5: 10992 | E5: 0 | F5: INDEPENDENT
A6: 1. Register cross-check | B6: 2024 | C6: 11149 | D6: 11149 | E6: 0 | F6: INDEPENDENT
A7: 2. PG pipeline | B7: 2024 | C7: 2707 | D7: 2717 | E7: 0.00368053 | F7: HELD-OUT TARGET, SHARED PUBLISHER
A8: 3. PG coverage factor | B8: 2024 | C8: 4630 | D8: 4629 | E8: 0.00021602938 | F8: NOT INDEPENDENT, INTERNAL CONSISTENCY ONLY
A11: Check | B11: Independence | C11: What it does and does not establish
A12: 1. Register cross-check | B12: INDEPENDENT | C12: The scraped National Medical Commission register and the Tamil Nadu Medical Council's own workbook are separate systems maintained by different bodies. Neither was used to build the other. This is the only fully independent check of the three, and it is the strongest evidence that the register inflow is right.
A13: 2. PG pipeline | B13: HELD-OUT TARGET, SHARED PUBLISHER | C13: Predicted pass-outs are built from seats, the fill rate and the completion rate. The pass-out figures they are compared against were NOT used to fit any of those three, so the target is genuinely held out. However, both the seat file and the pass-out file come from the same publisher, Dr. M.G.R. Medical University, so a systematic error in that university's reporting would not be caught. Treat this as a real but partial test.
A14: 3. PG coverage factor | B14: NOT INDEPENDENT, INTERNAL CONSISTENCY ONLY | C14: The 1.407 factor was itself derived by comparing the MGRMU basis with the Selection Committee total, and it is then checked against the Selection Committee total. That is circular. It confirms the scaling was applied correctly and that the two sources reconcile arithmetically, which is worth knowing, but it is not evidence that the model predicts anything. It should not be presented as validation.
A16: External-entrant residual, year | B16: Value
A17: 2021 | B17: 4583
A18: 2022 | B18: 6328
A19: 2023 | B19: 4961
A20: 2024 | B20: 5456
A21: 2025 | B21: 5577
A22: Mean, held flat in projection | B22: 5381
A24: A fourth check is internal rather than external: the stock identity. Active doctors in year t must equal active doctors in t-1 plus entrants minus exits.
A25: The model verifies this to under one doctor across all 39 year transitions, and the Projection sheet reproduces it as a live formula in column Q.
A26: This catches accounting errors, which it did: it is how the participation-weighting error in the exit calculation was found. It cannot catch a wrong assumption.

Sheet Cadre parameters
A1: Cadre | B1: Group | C1: Course length, years | D1: Fill rate | E1: Completion rate | F1: Completion basis | G1: Sanctioned seats 2050, frozen path | H1: Sanctioned seats 2050, trend path
A2: BSc Nursing | B2: Nursing | C2: 4 | D2: 0.96937572 | E2: 0.75961397 | F2: observed (1 cohort match) | G2: 18910 | H2: 32247
A3: MSc Nursing | B3: Nursing | C3: 2 | D3: 0.59101862 | E3: 0.89082278 | F3: observed (3 cohort matches) | G3: 1256 | H3: 1963
A4: Post Basic BSc Nursing | B4: Nursing | C4: 2 | D4: 0.48149211 | E4: 0.80125523 | F4: observed (3 cohort matches) | G4: 1705 | H4: 1430
A5: BDS | B5: Dental | C5: 5 | D5: 0.90762082 | E5: 0.91039427 | F5: assumed | G5: 2200 | H5: 2480
A6: MDS | B6: Dental | C6: 3 | D6: 0.91916168 | E6: 0.99122769 | F6: observed (2 cohort matches) | G6: 435 | H6: 613
A7: B.Pharm | B7: Pharmacy | C7: 4 | D7: 0.9347929 | E7: 0.82199313 | F7: observed (1 cohort match) | G7: 10130 | H7: 17930
A8: M.Pharm | B8: Pharmacy | C8: 2 | D8: 0.6743413 | E8: 0.93141153 | F8: observed (3 cohort matches) | G8: 2309 | H8: 5256
A9: Pharm.D | B9: Pharmacy | C9: 6 | D9: 0.91849817 | E9: 0.91039427 | F9: assumed | G9: 1560 | H9: 3630
A10: BPT | B10: Rehabilitation | C10: 5 | D10: 0.89085356 | E10: 0.91039427 | F10: assumed | G10: 3348 | H10: 4943
A11: MPT | B11: Rehabilitation | C11: 2 | D11: 0.9442953 | E11: 0.97506925 | F11: observed (3 cohort matches) | G11: 375 | H11: 412
A12: BOT | B12: Rehabilitation | C12: 5 | D12: 0.67456556 | E12: 0.91039427 | F12: assumed | G12: 728 | H12: 1256
A13: MOT | B13: Rehabilitation | C13: 2 | D13: 0.73846154 | E13: 0.93333333 | F13: observed (3 cohort matches) | G13: 39 | H13: 87
... A21: AHS PG (allied) | B21: Allied health | C21: 2 | D21: 0.65160158 | E21: 0.91039427 | F21: observed (3 cohort matches) | G21: 472 | H21: 562
A23: Fill rate is admissions divided by sanctioned seats, pooled across all observed years for that cadre. Estimated, not assumed.
A24: Completion rate is pass-outs divided by the admissions of the cohort that entered one course length earlier. Marked observed where a
A25: cohort could be matched inside the observed window, assumed otherwise. Assumed cases take 91%, the median of the 11 observed values.
A26: Columns D and E are the live inputs to every formula on the Cadre output sheet.

Sheet Cadre seats
A1: Year | B1: Basis | C1: BSc Nursing | D1: MSc Nursing | E1: Post Basic BSc Nursing | F1: BDS | G1: MDS | H1: B.Pharm | I1: M.Pharm | J1: Pharm.D | K1: BPT | L1: MPT | M1: BOT | N1: MOT | O1: BAMS (Ayurveda) | P1: BSMS (Siddha) | Q1: BUMS (Unani) | R1: BNYS (Naturopathy) | S1: BHMS (Homoeopathy) | T1: MD Siddha | U1: MD Homoeopathy | V1: AHS PG (allied)
A2: 2021 | B2: Observed | C2: 13689 | D2: 1099 | E2: 1775 | F2: 2060 | G2: 373 | H2: 7230 | I2: 1270 | J2: 720 | K2: 2898 | L2: 367 | M2: 568 | N2: 30 | O2: 370 | P2: 650 | Q2: 60 | R2: 1660 | S2: 910 | T2: 152 | U2: 55 | V2: 467
A3: 2022 | B3: Observed | C3: 14588 | D3: 1019 | E3: 1765 | F3: 2150 | G3: 375 | H3: 7270 | I3: 1058 | J3: 870 | K3: 3048 | L3: 369 | M3: 618 | N3: 22 | O3: 370 | P3: 790 | Q3: 60 | R3: 1658 | S3: 910 | T3: 152 | U3: 61 | V3: 390
A4: 2023 | B4: Observed | C4: 15887 | D4: 1191 | E4: 1725 | F4: 2200 | G4: 392 | H4: 8350 | I4: 1558 | J4: 1050 | K4: 3148 | L4: 379 | M4: 618 | N4: 39 | O4: 312 | P4: 890 | Q4: 54 | R4: 1660 | S4: 830 | T4: 152 | U4: 66 | V4: 480
A5: 2024 | B5: Observed | C5: 17483 | D5: 1256 | E5: 1705 | F5: 2150 | G5: 429 | H5: 9270 | I5: 1927 | J5: 1260 | K5: 3348 | L5: 375 | M5: 728 | N5: 39 | O5: 330 | P5: 1040 | Q5: 51 | R5: 1760 | S5: 870 | T5: 152 | U5: 102 | V5: 470
A6: 2025 | B6: Observed | C6: 18910 | D6: 1320.3 | E6: 1680 | F6: 2200 | G6: 435 | H6: 10130 | I6: 2309 | J6: 1560 | K6: 3493 | L6: 378.4 | M6: 776 | N6: 43.4 | O6: 330 | P6: 1040 | Q6: 60 | R6: 2060 | S6: 850 | T6: 152 | U6: 96 | V6: 472
A7: 2026 | B7: Projected, trend path | C7: 20243.7 | D7: 1384.6 | E7: 1655 | F7: 2228 | G7: 452.8 | H7: 10910 | I7: 2603.7 | J7: 1767 | K7: 3638 | L7: 381.8 | M7: 824 | N7: 47.8 | O7: 318 | P7: 1143 | Q7: 59.1 | R7: 2150.2 | S7: 834 | T7: 152 | U7: 108.3 | V7: 481
A8: 2027 | B8: Projected, trend path | C8: 21577.4 | D8: 1448.9 | E8: 1630 | F8: 2256 | G8: 470.6 | H8: 11690 | I8: 2898.4 | J8: 1974 | K8: 3783 | L8: 385.2 | M8: 872 | N8: 52.2 | O8: 306 | P8: 1246 | Q8: 58.2 | R8: 2240.4 | S8: 818 | T8: 152 | U8: 120.6 | V8: 490
A9: 2028 | B9: Projected, trend path | C9: 22911.1 | D9: 1513.2 | E9: 1605 | F9: 2284 | G9: 488.4 | H9: 12470 | I9: 3193.1 | J9: 2181 | K9: 3928 | L9: 388.6 | M9: 920 | N9: 56.6 | O9: 294 | P9: 1349 | Q9: 57.3 | R9: 2330.6 | S9: 802 | T9: 152 | U9: 132.9 | V9: 499
A10: 2029 | B10: Projected, trend path | C10: 24244.8 | D10: 1577.5 | E10: 1580 | F10: 2312 | G10: 506.2 | H10: 13250 | I10: 3487.8 | J10: 2388 | K10: 4073 | L10: 392 | M10: 968 | N10: 61 | O10: 282 | P10: 1452 | Q10: 56.4 | R10: 2420.8 | S10: 786 | T10: 152 | U10: 145.2 | V10: 508
A11: 2030 | B11: Projected, trend path | C11: 25578.5 | D11: 1641.8 | E11: 1555 | F11: 2340 | G11: 524 | H11: 14030 | I11: 3782.5 | J11: 2595 | K11: 4218 | L11: 395.4 | M11: 1016 | N11: 65.4 | O11: 270 | P11: 1555 | Q11: 55.5 | R11: 2511 | S11: 770 | T11: 152 | U11: 157.5 | V11: 517
A12: 2031 | B12: Projected, trend path | C12: 26912.2 | D12: 1706.1 | E12: 1530 | F12: 2368 | G12: 541.8 | H12: 14810 | I12: 4077.2 | J12: 2802 | K12: 4363 | L12: 398.8 | M12: 1064 | N12: 69.8 | O12: 258 | P12: 1658 | Q12: 54.6 | R12: 2601.2 | S12: 754 | T12: 152 | U12: 169.8 | V12: 526
A13: 2032 | B13: Projected, trend path | C13: 28245.9 | D13: 1770.4 | E13: 1505 | F13: 2396 | G13: 559.6 | H13: 15590 | I13: 4371.9 | J13: 3009 | K13: 4508 | L13: 402.2 | M13: 1112 | N13: 74.2 | O13: 246 | P13: 1761 | Q13: 53.7 | R13: 2691.4 | S13: 738 | T13: 152 | U13: 182.1 | V13: 535
... A31: 2050 | B31: Projected, trend path | C31: 32247 | D31: 1963.3 | E31: 1430 | F31: 2480 | G31: 613 | H31: 17930 | I31: 5256 | J31: 3630 | K31: 4943 | L31: 412.4 | M31: 1256 | N31: 87.4 | O31: 210 | P31: 2070 | Q31: 51 | R31: 2962 | S31: 690 | T31: 152 | U31: 219 | V31: 562
A33: Sanctioned seats by cadre and year, trend path. Observed to 2025, then the fitted linear trend continued to 2035 and held flat.
A34: Growth is fitted in LEVELS, never as a compound rate. The frozen-path alternative is on the Cadre parameters sheet.
A35: This sheet is the seat input that every formula on the Cadre output sheet reads.

Sheet Cadre output
A1: Year | B1: BSc Nursing | C1: MSc Nursing | D1: Post Basic BSc Nursing | E1: BDS | F1: MDS | G1: B.Pharm | H1: M.Pharm | I1: Pharm.D | J1: BPT | K1: MPT | L1: BOT | M1: MOT | N1: BAMS (Ayurveda) | O1: BSMS (Siddha) | P1: BUMS (Unani) | Q1: BNYS (Naturopathy) | R1: BHMS (Homoeopathy) | S1: MD Siddha | T1: MD Homoeopathy | U1: AHS PG (allied) | V1: Total, these cadres
A2: 2027 | B2: ='Cadre seats'!C4*'Cadre parameters'!$D$2*'Cadre parameters'!$E$2 | C2: ='Cadre seats'!D6*'Cadre parameters'!$D$3*'Cadre parameters'!$E$3 | D2: ='Cadre seats'!E6*'Cadre parameters'!$D$4*'Cadre parameters'!$E$4 | E2: ='Cadre seats'!F3*'Cadre parameters'!$D$5*'Cadre parameters'!$E$5 | F2: ='Cadre seats'!G5*'Cadre parameters'!$D$6*'Cadre parameters'!$E$6 | G2: ='Cadre seats'!H4*'Cadre parameters'!$D$7*'Cadre parameters'!$E$7 | H2: ='Cadre seats'!I6*'Cadre parameters'!$D$8*'Cadre parameters'!$E$8 | I2: ='Cadre seats'!J2*'Cadre parameters'!$D$9*'Cadre parameters'!$E$9 | J2: ='Cadre seats'!K3*'Cadre parameters'!$D$10*'Cadre parameters'!$E$10 | K2: ='Cadre seats'!L6*'Cadre parameters'!$D$11*'Cadre parameters'!$E$11 | L2: ='Cadre seats'!M3*'Cadre parameters'!$D$12*'Cadre parameters'!$E$12 | M2: ='Cadre seats'!N6*'Cadre parameters'!$D$13*'Cadre parameters'!$E$13 | N2: ='Cadre seats'!O2*'Cadre parameters'!$D$14*'Cadre parameters'!$E$14 | O2: ='Cadre seats'!P2*'Cadre parameters'!$D$15*'Cadre parameters'!$E$15 | P2: ='Cadre seats'!Q2*'Cadre parameters'!$D$16*'Cadre parameters'!$E$16 | Q2: ='Cadre seats'!R2*'Cadre parameters'!$D$17*'Cadre parameters'!$E$17 | R2: ='Cadre seats'!S2*'Cadre parameters'!$D$18*'Cadre parameters'!$E$18 | S2: ='Cadre seats'!T5*'Cadre parameters'!$D$19*'Cadre parameters'!$E$19 | T2: ='Cadre seats'!U5*'Cadre parameters'!$D$20*'Cadre parameters'!$E$20 | U2: ='Cadre seats'!V6*'Cadre parameters'!$D$21*'Cadre parameters'!$E$21 | V2: =SUM(B2:U2)
A3: 2028 | B3: ='Cadre seats'!C5*'Cadre parameters'!$D$2*'Cadre parameters'!$E$2 | C3: ='Cadre seats'!D7*'Cadre parameters'!$D$3*'Cadre parameters'!$E$3 | D3: ='Cadre seats'!E7*'Cadre parameters'!$D$4*'Cadre parameters'!$E$4 | E3: ='Cadre seats'!F4*'Cadre parameters'!$D$5*'Cadre parameters'!$E$5 | F3: ='Cadre seats'!G6*'Cadre parameters'!$D$6*'Cadre parameters'!$E$6 | G3: ='Cadre seats'!H5*'Cadre parameters'!$D$7*'Cadre parameters'!$E$7 | H3: ='Cadre seats'!I7*'Cadre parameters'!$D$8*'Cadre parameters'!$E$8 | I3: ='Cadre seats'!J3*'Cadre parameters'!$D$9*'Cadre parameters'!$E$9 | J3: ='Cadre seats'!K4*'Cadre parameters'!$D$10*'Cadre parameters'!$E$10 | K3: ='Cadre seats'!L7*'Cadre parameters'!$D$11*'Cadre parameters'!$E$11 | L3: ='Cadre seats'!M4*'Cadre parameters'!$D$12*'Cadre parameters'!$E$12 | M3: ='Cadre seats'!N7*'Cadre parameters'!$D$13*'Cadre parameters'!$E$13 | N3: ='Cadre seats'!O3*'Cadre parameters'!$D$14*'Cadre parameters'!$E$14 | O3: ='Cadre seats'!P3*'Cadre parameters'!$D$15*'Cadre parameters'!$E$15 | P3: ='Cadre seats'!Q3*'Cadre parameters'!$D$16*'Cadre parameters'!$E$16 | Q3: ='Cadre seats'!R3*'Cadre parameters'!$D$17*'Cadre parameters'!$E$17 | R3: ='Cadre seats'!S3*'Cadre parameters'!$D$18*'Cadre parameters'!$E$18 | S3: ='Cadre seats'!T6*'Cadre parameters'!$D$19*'Cadre parameters'!$E$19 | T3: ='Cadre seats'!U6*'Cadre parameters'!$D$20*'Cadre parameters'!$E$20 | U3: ='Cadre seats'!V7*'Cadre parameters'!$D$21*'Cadre parameters'!$E$21 | V3: =SUM(B3:U3)
A4: 2029 | B4: ='Cadre seats'!C6*'Cadre parameters'!$D$2*'Cadre parameters'!$E$2 | C4: ='Cadre seats'!D8*'Cadre parameters'!$D$3*'Cadre parameters'!$E$3 | D4: ='Cadre seats'!E8*'Cadre parameters'!$D$4*'Cadre parameters'!$E$4 | E4: ='Cadre seats'!F5*'Cadre parameters'!$D$5*'Cadre parameters'!$E$5 | F4: ='Cadre seats'!G7*'Cadre parameters'!$D$6*'Cadre parameters'!$E$6 | G4: ='Cadre seats'!H6*'Cadre parameters'!$D$7*'Cadre parameters'!$E$7 | H4: ='Cadre seats'!I8*'Cadre parameters'!$D$8*'Cadre parameters'!$E$8 | I4: ='Cadre seats'!J4*'Cadre parameters'!$D$9*'Cadre parameters'!$E$9 | J4: ='Cadre seats'!K5*'Cadre parameters'!$D$10*'Cadre parameters'!$E$10 | K4: ='Cadre seats'!L8*'Cadre parameters'!$D$11*'Cadre parameters'!$E$11 | L4: ='Cadre seats'!M5*'Cadre parameters'!$D$12*'Cadre parameters'!$E$12 | M4: ='Cadre seats'!N8*'Cadre parameters'!$D$13*'Cadre parameters'!$E$13 | N4: ='Cadre seats'!O4*'Cadre parameters'!$D$14*'Cadre parameters'!$E$14 | O4: ='Cadre seats'!P4*'Cadre parameters'!$D$15*'Cadre parameters'!$E$15 | P4: ='Cadre seats'!Q4*'Cadre parameters'!$D$16*'Cadre parameters'!$E$16 | Q4: ='Cadre seats'!R4*'Cadre parameters'!$D$17*'Cadre parameters'!$E$17 | R4: ='Cadre seats'!S4*'Cadre parameters'!$D$18*'Cadre parameters'!$E$18 | S4: ='Cadre seats'!T7*'Cadre parameters'!$D$19*'Cadre parameters'!$E$19 | T4: ='Cadre seats'!U7*'Cadre parameters'!$D$20*'Cadre parameters'!$E$20 | U4: ='Cadre seats'!V8*'Cadre parameters'!$D$21*'Cadre parameters'!$E$21 | V4: =SUM(B4:U4)
A5: 2030 | B5: ='Cadre seats'!C7*'Cadre parameters'!$D$2*'Cadre parameters'!$E$2 | C5: ='Cadre seats'!D9*'Cadre parameters'!$D$3*'Cadre parameters'!$E$3 | D5: ='Cadre seats'!E9*'Cadre parameters'!$D$4*'Cadre parameters'!$E$4 | E5: ='Cadre seats'!F6*'Cadre parameters'!$D$5*'Cadre parameters'!$E$5 | F5: ='Cadre seats'!G8*'Cadre parameters'!$D$6*'Cadre parameters'!$E$6 | G5: ='Cadre seats'!H7*'Cadre parameters'!$D$7*'Cadre parameters'!$E$7 | H5: ='Cadre seats'!I9*'Cadre parameters'!$D$8*'Cadre parameters'!$E$8 | I5: ='Cadre seats'!J5*'Cadre parameters'!$D$9*'Cadre parameters'!$E$9 | J5: ='Cadre seats'!K6*'Cadre parameters'!$D$10*'Cadre parameters'!$E$10 | K5: ='Cadre seats'!L9*'Cadre parameters'!$D$11*'Cadre parameters'!$E$11 | L5: ='Cadre seats'!M6*'Cadre parameters'!$D$12*'Cadre parameters'!$E$12 | M5: ='Cadre seats'!N9*'Cadre parameters'!$D$13*'Cadre parameters'!$E$13 | N5: ='Cadre seats'!O5*'Cadre parameters'!$D$14*'Cadre parameters'!$E$14 | O5: ='Cadre seats'!P5*'Cadre parameters'!$D$15*'Cadre parameters'!$E$15 | P5: ='Cadre seats'!Q5*'Cadre parameters'!$D$16*'Cadre parameters'!$E$16 | Q5: ='Cadre seats'!R5*'Cadre parameters'!$D$17*'Cadre parameters'!$E$17 | R5: ='Cadre seats'!S5*'Cadre parameters'!$D$18*'Cadre parameters'!$E$18 | S5: ='Cadre seats'!T8*'Cadre parameters'!$D$19*'Cadre parameters'!$E$19 | T5: ='Cadre seats'!U8*'Cadre parameters'!$D$20*'Cadre parameters'!$E$20 | U5: ='Cadre seats'!V9*'Cadre parameters'!$D$21*'Cadre parameters'!$E$21 | V5: =SUM(B5:U5)
A6: 2031 | B6: ='Cadre seats'!C8*'Cadre parameters'!$D$2*'Cadre parameters'!$E$2 | C6: ='Cadre seats'!D10*'Cadre parameters'!$D$3*'Cadre parameters'!$E$3 | D6: ='Cadre seats'!E10*'Cadre parameters'!$D$4*'Cadre parameters'!$E$4 | E6: ='Cadre seats'!F7*'Cadre parameters'!$D$5*'Cadre parameters'!$E$5 | F6: ='Cadre seats'!G9*'Cadre parameters'!$D$6*'Cadre parameters'!$E$6 | G6: ='Cadre seats'!H8*'Cadre parameters'!$D$7*'Cadre parameters'!$E$7 | H6: ='Cadre seats'!I10*'Cadre parameters'!$D$8*'Cadre parameters'!$E$8 | I6: ='Cadre seats'!J6*'Cadre parameters'!$D$9*'Cadre parameters'!$E$9 | J6: ='Cadre seats'!K7*'Cadre parameters'!$D$10*'Cadre parameters'!$E$10 | K6: ='Cadre seats'!L10*'Cadre parameters'!$D$11*'Cadre parameters'!$E$11 | L6: ='Cadre seats'!M7*'Cadre parameters'!$D$12*'Cadre parameters'!$E$12 | M6: ='Cadre seats'!N10*'Cadre parameters'!$D$13*'Cadre parameters'!$E$13 | N6: ='Cadre seats'!O6*'Cadre parameters'!$D$14*'Cadre parameters'!$E$14 | O6: ='Cadre seats'!P6*'Cadre parameters'!$D$15*'Cadre parameters'!$E$15 | P6: ='Cadre seats'!Q6*'Cadre parameters'!$D$16*'Cadre parameters'!$E$16 | Q6: ='Cadre seats'!R6*'Cadre parameters'!$D$17*'Cadre parameters'!$E$17 | R6: ='Cadre seats'!S6*'Cadre parameters'!$D$18*'Cadre parameters'!$E$18 | S6: ='Cadre seats'!T9*'Cadre parameters'!$D$19*'Cadre parameters'!$E$19 | T6: ='Cadre seats'!U9*'Cadre parameters'!$D$20*'Cadre parameters'!$E$20 | U6: ='Cadre seats'!V10*'Cadre parameters'!$D$21*'Cadre parameters'!$E$21 | V6: =SUM(B6:U6)
A7: 2032 | B7: ='Cadre seats'!C9*'Cadre parameters'!$D$2*'Cadre parameters'!$E$2 | C7: ='Cadre seats'!D11*'Cadre parameters'!$D$3*'Cadre parameters'!$E$3 | D7: ='Cadre seats'!E11*'Cadre parameters'!$D$4*'Cadre parameters'!$E$4 | E7: ='Cadre seats'!F8*'Cadre parameters'!$D$5*'Cadre parameters'!$E$5 | F7: ='Cadre seats'!G10*'Cadre parameters'!$D$6*'Cadre parameters'!$E$6 | G7: ='Cadre seats'!H9*'Cadre parameters'!$D$7*'Cadre parameters'!$E$7 | H7: ='Cadre seats'!I11*'Cadre parameters'!$D$8*'Cadre parameters'!$E$8 | I7: ='Cadre seats'!J7*'Cadre parameters'!$D$9*'Cadre parameters'!$E$9 | J7: ='Cadre seats'!K8*'Cadre parameters'!$D$10*'Cadre parameters'!$E$10 | K7: ='Cadre seats'!L11*'Cadre parameters'!$D$11*'Cadre parameters'!$E$11 | L7: ='Cadre seats'!M8*'Cadre parameters'!$D$12*'Cadre parameters'!$E$12 | M7: ='Cadre seats'!N11*'Cadre parameters'!$D$13*'Cadre parameters'!$E$13 | N7: ='Cadre seats'!O7*'Cadre parameters'!$D$14*'Cadre parameters'!$E$14 | O7: ='Cadre seats'!P7*'Cadre parameters'!$D$15*'Cadre parameters'!$E$15 | P7: ='Cadre seats'!Q7*'Cadre parameters'!$D$16*'Cadre parameters'!$E$16 | Q7: ='Cadre seats'!R7*'Cadre parameters'!$D$17*'Cadre parameters'!$E$17 | R7: ='Cadre seats'!S7*'Cadre parameters'!$D$18*'Cadre parameters'!$E$18 | S7: ='Cadre seats'!T10*'Cadre parameters'!$D$19*'Cadre parameters'!$E$19 | T7: ='Cadre seats'!U10*'Cadre parameters'!$D$20*'Cadre parameters'!$E$20 | U7: ='Cadre seats'!V11*'Cadre parameters'!$D$21*'Cadre parameters'!$E$21 | V7: =SUM(B7:U7)
A8: 2033 | B8: ='Cadre seats'!C10*'Cadre parameters'!$D$2*'Cadre parameters'!$E$2 | C8: ='Cadre seats'!D12*'Cadre parameters'!$D$3*'Cadre parameters'!$E$3 | D8: ='Cadre seats'!E12*'Cadre parameters'!$D$4*'Cadre parameters'!$E$4 | E8: ='Cadre seats'!F9*'Cadre parameters'!$D$5*'Cadre parameters'!$E$5 | F8: ='Cadre seats'!G11*'Cadre parameters'!$D$6*'Cadre parameters'!$E$6 | G8: ='Cadre seats'!H10*'Cadre parameters'!$D$7*'Cadre parameters'!$E$7 | H8: ='Cadre seats'!I12*'Cadre parameters'!$D$8*'Cadre parameters'!$E$8 | I8: ='Cadre seats'!J8*'Cadre parameters'!$D$9*'Cadre parameters'!$E$9 | J8: ='Cadre seats'!K9*'Cadre parameters'!$D$10*'Cadre parameters'!$E$10 | K8: ='Cadre seats'!L12*'Cadre parameters'!$D$11*'Cadre parameters'!$E$11 | L8: ='Cadre seats'!M9*'Cadre parameters'!$D$12*'Cadre parameters'!$E$12 | M8: ='Cadre seats'!N12*'Cadre parameters'!$D$13*'Cadre parameters'!$E$13 | N8: ='Cadre seats'!O8*'Cadre parameters'!$D$14*'Cadre parameters'!$E$14 | O8: ='Cadre seats'!P8*'Cadre parameters'!$D$15*'Cadre parameters'!$E$15 | P8: ='Cadre seats'!Q8*'Cadre parameters'!$D$16*'Cadre parameters'!$E$16 | Q8: ='Cadre seats'!R8*'Cadre parameters'!$D$17*'Cadre parameters'!$E$17 | R8: ='Cadre seats'!S8*'Cadre parameters'!$D$18*'Cadre parameters'!$E$18 | S8: ='Cadre seats'!T11*'Cadre parameters'!$D$19*'Cadre parameters'!$E$19 | T8: ='Cadre seats'!U11*'Cadre parameters'!$D$20*'Cadre parameters'!$E$20 | U8: ='Cadre seats'!V12*'Cadre parameters'!$D$21*'Cadre parameters'!$E$21 | V8: =SUM(B8:U8)
A9: 2034 | B9: ='Cadre seats'!C11*'Cadre parameters'!$D$2*'Cadre parameters'!$E$2 | C9: ='Cadre seats'!D13*'Cadre parameters'!$D$3*'Cadre parameters'!$E$3 | D9: ='Cadre seats'!E13*'Cadre parameters'!$D$4*'Cadre parameters'!$E$4 | E9: ='Cadre seats'!F10*'Cadre parameters'!$D$5*'Cadre parameters'!$E$5 | F9: ='Cadre seats'!G12*'Cadre parameters'!$D$6*'Cadre parameters'!$E$6 | G9: ='Cadre seats'!H11*'Cadre parameters'!$D$7*'Cadre parameters'!$E$7 | H9: ='Cadre seats'!I13*'Cadre parameters'!$D$8*'Cadre parameters'!$E$8 | I9: ='Cadre seats'!J9*'Cadre parameters'!$D$9*'Cadre parameters'!$E$9 | J9: ='Cadre seats'!K10*'Cadre parameters'!$D$10*'Cadre parameters'!$E$10 | K9: ='Cadre seats'!L13*'Cadre parameters'!$D$11*'Cadre parameters'!$E$11 | L9: ='Cadre seats'!M10*'Cadre parameters'!$D$12*'Cadre parameters'!$E$12 | M9: ='Cadre seats'!N13*'Cadre parameters'!$D$13*'Cadre parameters'!$E$13 | N9: ='Cadre seats'!O9*'Cadre parameters'!$D$14*'Cadre parameters'!$E$14 | O9: ='Cadre seats'!P9*'Cadre parameters'!$D$15*'Cadre parameters'!$E$15 | P9: ='Cadre seats'!Q9*'Cadre parameters'!$D$16*'Cadre parameters'!$E$16 | Q9: ='Cadre seats'!R9*'Cadre parameters'!$D$17*'Cadre parameters'!$E$17 | R9: ='Cadre seats'!S9*'Cadre parameters'!$D$18*'Cadre parameters'!$E$18 | S9: ='Cadre seats'!T12*'Cadre parameters'!$D$19*'Cadre parameters'!$E$19 | T9: ='Cadre seats'!U12*'Cadre parameters'!$D$20*'Cadre parameters'!$E$20 | U9: ='Cadre seats'!V13*'Cadre parameters'!$D$21*'Cadre parameters'!$E$21 | V9: =SUM(B9:U9)
A10: 2035 | B10: ='Cadre seats'!C12*'Cadre parameters'!$D$2*'Cadre parameters'!$E$2 | C10: ='Cadre seats'!D14*'Cadre parameters'!$D$3*'Cadre parameters'!$E$3 | D10: ='Cadre seats'!E14*'Cadre parameters'!$D$4*'Cadre parameters'!$E$4 | E10: ='Cadre seats'!F11*'Cadre parameters'!$D$5*'Cadre parameters'!$E$5 | F10: ='Cadre seats'!G13*'Cadre parameters'!$D$6*'Cadre parameters'!$E$6 | G10: ='Cadre seats'!H12*'Cadre parameters'!$D$7*'Cadre parameters'!$E$7 | H10: ='Cadre seats'!I14*'Cadre parameters'!$D$8*'Cadre parameters'!$E$8 | I10: ='Cadre seats'!J10*'Cadre parameters'!$D$9*'Cadre parameters'!$E$9 | J10: ='Cadre seats'!K11*'Cadre parameters'!$D$10*'Cadre parameters'!$E$10 | K10: ='Cadre seats'!L14*'Cadre parameters'!$D$11*'Cadre parameters'!$E$11 | L10: ='Cadre seats'!M11*'Cadre parameters'!$D$12*'Cadre parameters'!$E$12 | M10: ='Cadre seats'!N14*'Cadre parameters'!$D$13*'Cadre parameters'!$E$13 | N10: ='Cadre seats'!O10*'Cadre parameters'!$D$14*'Cadre parameters'!$E$14 | O10: ='Cadre seats'!P10*'Cadre parameters'!$D$15*'Cadre parameters'!$E$15 | P10: ='Cadre seats'!Q10*'Cadre parameters'!$D$16*'Cadre parameters'!$E$16 | Q10: ='Cadre seats'!R10*'Cadre parameters'!$D$17*'Cadre parameters'!$E$17 | R10: ='Cadre seats'!S10*'Cadre parameters'!$D$18*'Cadre parameters'!$E$18 | S10: ='Cadre seats'!T13*'Cadre parameters'!$D$19*'Cadre parameters'!$E$19 | T10: ='Cadre seats'!U13*'Cadre parameters'!$D$20*'Cadre parameters'!$E$20 | U10: ='Cadre seats'!V14*'Cadre parameters'!$D$21*'Cadre parameters'!$E$21 | V10: =SUM(B10:U10)
A11: 2036 | B11: ='Cadre seats'!C13*'Cadre parameters'!$D$2*'Cadre parameters'!$E$2 | C11: ='Cadre seats'!D15*'Cadre parameters'!$D$3*'Cadre parameters'!$E$3 | D11: ='Cadre seats'!E15*'Cadre parameters'!$D$4*'Cadre parameters'!$E$4 | E11: ='Cadre seats'!F12*'Cadre parameters'!$D$5*'Cadre parameters'!$E$5 | F11: ='Cadre seats'!G14*'Cadre parameters'!$D$6*'Cadre parameters'!$E$6 | G11: ='Cadre seats'!H13*'Cadre parameters'!$D$7*'Cadre parameters'!$E$7 | H11: ='Cadre seats'!I15*'Cadre parameters'!$D$8*'Cadre parameters'!$E$8 | I11: ='Cadre seats'!J11*'Cadre parameters'!$D$9*'Cadre parameters'!$E$9 | J11: ='Cadre seats'!K12*'Cadre parameters'!$D$10*'Cadre parameters'!$E$10 | K11: ='Cadre seats'!L15*'Cadre parameters'!$D$11*'Cadre parameters'!$E$11 | L11: ='Cadre seats'!M12*'Cadre parameters'!$D$12*'Cadre parameters'!$E$12 | M11: ='Cadre seats'!N15*'Cadre parameters'!$D$13*'Cadre parameters'!$E$13 | N11: ='Cadre seats'!O11*'Cadre parameters'!$D$14*'Cadre parameters'!$E$14 | O11: ='Cadre seats'!P11*'Cadre parameters'!$D$15*'Cadre parameters'!$E$15 | P11: ='Cadre seats'!Q11*'Cadre parameters'!$D$16*'Cadre parameters'!$E$16 | Q11: ='Cadre seats'!R11*'Cadre parameters'!$D$17*'Cadre parameters'!$E$17 | R11: ='Cadre seats'!S11*'Cadre parameters'!$D$18*'Cadre parameters'!$E$18 | S11: ='Cadre seats'!T14*'Cadre parameters'!$D$19*'Cadre parameters'!$E$19 | T11: ='Cadre seats'!U14*'Cadre parameters'!$D$20*'Cadre parameters'!$E$20 | U11: ='Cadre seats'!V15*'Cadre parameters'!$D$21*'Cadre parameters'!$E$21 | V11: =SUM(B11:U11)
A12: 2037 | B12: ='Cadre seats'!C14*'Cadre parameters'!$D$2*'Cadre parameters'!$E$2 | C12: ='Cadre seats'!D16*'Cadre parameters'!$D$3*'Cadre parameters'!$E$3 | D12: ='Cadre seats'!E16*'Cadre parameters'!$D$4*'Cadre parameters'!$E$4 | E12: ='Cadre seats'!F13*'Cadre parameters'!$D$5*'Cadre parameters'!$E$5 | F12: ='Cadre seats'!G15*'Cadre parameters'!$D$6*'Cadre parameters'!$E$6 | G12: ='Cadre seats'!H14*'Cadre parameters'!$D$7*'Cadre parameters'!$E$7 | H12: ='Cadre seats'!I16*'Cadre parameters'!$D$8*'Cadre parameters'!$E$8 | I12: ='Cadre seats'!J12*'Cadre parameters'!$D$9*'Cadre parameters'!$E$9 | J12: ='Cadre seats'!K13*'Cadre parameters'!$D$10*'Cadre parameters'!$E$10 | K12: ='Cadre seats'!L16*'Cadre parameters'!$D$11*'Cadre parameters'!$E$11 | L12: ='Cadre seats'!M13*'Cadre parameters'!$D$12*'Cadre parameters'!$E$12 | M12: ='Cadre seats'!N16*'Cadre parameters'!$D$13*'Cadre parameters'!$E$13 | N12: ='Cadre seats'!O12*'Cadre parameters'!$D$14*'Cadre parameters'!$E$14 | O12: ='Cadre seats'!P12*'Cadre parameters'!$D$15*'Cadre parameters'!$E$15 | P12: ='Cadre seats'!Q12*'Cadre parameters'!$D$16*'Cadre parameters'!$E$16 | Q12: ='Cadre seats'!R12*'Cadre parameters'!$D$17*'Cadre parameters'!$E$17 | R12: ='Cadre seats'!S12*'Cadre parameters'!$D$18*'Cadre parameters'!$E$18 | S12: ='Cadre seats'!T15*'Cadre parameters'!$D$19*'Cadre parameters'!$E$19 | T12: ='Cadre seats'!U15*'Cadre parameters'!$D$20*'Cadre parameters'!$E$20 | U12: ='Cadre seats'!V16*'Cadre parameters'!$D$21*'Cadre parameters'!$E$21 | V12: =SUM(B12:U12)
A13: 2038 | B13: ='Cadre seats'!C15*'Cadre parameters'!$D$2*'Cadre parameters'!$E$2 | C13: ='Cadre seats'!D17*'Cadre parameters'!$D$3*'Cadre parameters'!$E$3 | D13: ='Cadre seats'!E17*'Cadre parameters'!$D$4*'Cadre parameters'!$E$4 | E13: ='Cadre seats'!F14*'Cadre parameters'!$D$5*'Cadre parameters'!$E$5 | F13: ='Cadre seats'!G16*'Cadre parameters'!$D$6*'Cadre parameters'!$E$6 | G13: ='Cadre seats'!H15*'Cadre parameters'!$D$7*'Cadre parameters'!$E$7 | H13: ='Cadre seats'!I17*'Cadre parameters'!$D$8*'Cadre parameters'!$E$8 | I13: ='Cadre seats'!J13*'Cadre parameters'!$D$9*'Cadre parameters'!$E$9 | J13: ='Cadre seats'!K14*'Cadre parameters'!$D$10*'Cadre parameters'!$E$10 | K13: ='Cadre seats'!L17*'Cadre parameters'!$D$11*'Cadre parameters'!$E$11 | L13: ='Cadre seats'!M14*'Cadre parameters'!$D$12*'Cadre parameters'!$E$12 | M13: ='Cadre seats'!N17*'Cadre parameters'!$D$13*'Cadre parameters'!$E$13 | N13: ='Cadre seats'!O13*'Cadre parameters'!$D$14*'Cadre parameters'!$E$14 | O13: ='Cadre seats'!P13*'Cadre parameters'!$D$15*'Cadre parameters'!$E$15 | P13: ='Cadre seats'!Q13*'Cadre parameters'!$D$16*'Cadre parameters'!$E$16 | Q13: ='Cadre seats'!R13*'Cadre parameters'!$D$17*'Cadre parameters'!$E$17 | R13: ='Cadre seats'!S13*'Cadre parameters'!$D$18*'Cadre parameters'!$E$18 | S13: ='Cadre seats'!T16*'Cadre parameters'!$D$19*'Cadre parameters'!$E$19 | T13: ='Cadre seats'!U16*'Cadre parameters'!$D$20*'Cadre parameters'!$E$20 | U13: ='Cadre seats'!V17*'Cadre parameters'!$D$21*'Cadre parameters'!$E$21 | V13: =SUM(B13:U13)
... A25: 2050 | B25: ='Cadre seats'!C27*'Cadre parameters'!$D$2*'Cadre parameters'!$E$2 | C25: ='Cadre seats'!D29*'Cadre parameters'!$D$3*'Cadre parameters'!$E$3 | D25: ='Cadre seats'!E29*'Cadre parameters'!$D$4*'Cadre parameters'!$E$4 | E25: ='Cadre seats'!F26*'Cadre parameters'!$D$5*'Cadre parameters'!$E$5 | F25: ='Cadre seats'!G28*'Cadre parameters'!$D$6*'Cadre parameters'!$E$6 | G25: ='Cadre seats'!H27*'Cadre parameters'!$D$7*'Cadre parameters'!$E$7 | H25: ='Cadre seats'!I29*'Cadre parameters'!$D$8*'Cadre parameters'!$E$8 | I25: ='Cadre seats'!J25*'Cadre parameters'!$D$9*'Cadre parameters'!$E$9 | J25: ='Cadre seats'!K26*'Cadre parameters'!$D$10*'Cadre parameters'!$E$10 | K25: ='Cadre seats'!L29*'Cadre parameters'!$D$11*'Cadre parameters'!$E$11 | L25: ='Cadre seats'!M26*'Cadre parameters'!$D$12*'Cadre parameters'!$E$12 | M25: ='Cadre seats'!N29*'Cadre parameters'!$D$13*'Cadre parameters'!$E$13 | N25: ='Cadre seats'!O25*'Cadre parameters'!$D$14*'Cadre parameters'!$E$14 | O25: ='Cadre seats'!P25*'Cadre parameters'!$D$15*'Cadre parameters'!$E$15 | P25: ='Cadre seats'!Q25*'Cadre parameters'!$D$16*'Cadre parameters'!$E$16 | Q25: ='Cadre seats'!R25*'Cadre parameters'!$D$17*'Cadre parameters'!$E$17 | R25: ='Cadre seats'!S25*'Cadre parameters'!$D$18*'Cadre parameters'!$E$18 | S25: ='Cadre seats'!T28*'Cadre parameters'!$D$19*'Cadre parameters'!$E$19 | T25: ='Cadre seats'!U28*'Cadre parameters'!$D$20*'Cadre parameters'!$E$20 | U25: ='Cadre seats'!V29*'Cadre parameters'!$D$21*'Cadre parameters'!$E$21 | V25: =SUM(B25:U25)
A27: WHAT THIS SHEET IS. The number of people qualifying in each cadre in each year. It is NOT a count of people practising.
A28: HOW EACH CELL IS BUILT. Sanctioned seats one course length earlier, taken from the Cadre seats sheet, multiplied by that cadre's
A29: fill rate and completion rate from the Cadre parameters sheet. Every cell is a live formula, so changing a rate moves the whole column.
A30: WHY IT STARTS AT 2027. Seat data begins in 2021 and the longest course here is six years, so 2021 to 2026 are only partly covered
A31: and would understate the total. 2027 is the first year in which every cadre has a source cohort.
A32: WHAT IS MISSING. GNM and ANM nursing appear in no source file, so nursing is degree level only. See the Not covered sheet.

Sheet Cadre by group
A1: Year | B1: AYUSH | C1: Allied health | D1: Dental | E1: Nursing | F1: Pharmacy | G1: Rehabilitation | H1: Total
A2: 2027 | B2: ='Cadre output'!N2+'Cadre output'!O2+'Cadre output'!P2+'Cadre output'!Q2+'Cadre output'!R2+'Cadre output'!S2+'Cadre output'!T2 | C2: ='Cadre output'!U2 | D2: ='Cadre output'!E2+'Cadre output'!F2 | E2: ='Cadre output'!B2+'Cadre output'!C2+'Cadre output'!D2 | F2: ='Cadre output'!G2+'Cadre output'!H2+'Cadre output'!I2 | G2: ='Cadre output'!J2+'Cadre output'!K2+'Cadre output'!L2+'Cadre output'!M2 | H2: =SUM(B2:G2)
A3: 2028 | B3: ='Cadre output'!N3+'Cadre output'!O3+'Cadre output'!P3+'Cadre output'!Q3+'Cadre output'!R3+'Cadre output'!S3+'Cadre output'!T3 | C3: ='Cadre output'!U3 | D3: ='Cadre output'!E3+'Cadre output'!F3 | E3: ='Cadre output'!B3+'Cadre output'!C3+'Cadre output'!D3 | F3: ='Cadre output'!G3+'Cadre output'!H3+'Cadre output'!I3 | G3: ='Cadre output'!J3+'Cadre output'!K3+'Cadre output'!L3+'Cadre output'!M3 | H3: =SUM(B3:G3)
A4: 2029 | B4: ='Cadre output'!N4+'Cadre output'!O4+'Cadre output'!P4+'Cadre output'!Q4+'Cadre output'!R4+'Cadre output'!S4+'Cadre output'!T4 | C4: ='Cadre output'!U4 | D4: ='Cadre output'!E4+'Cadre output'!F4 | E4: ='Cadre output'!B4+'Cadre output'!C4+'Cadre output'!D4 | F4: ='Cadre output'!G4+'Cadre output'!H4+'Cadre output'!I4 | G4: ='Cadre output'!J4+'Cadre output'!K4+'Cadre output'!L4+'Cadre output'!M4 | H4: =SUM(B4:G4)
A5: 2030 | B5: ='Cadre output'!N5+'Cadre output'!O5+'Cadre output'!P5+'Cadre output'!Q5+'Cadre output'!R5+'Cadre output'!S5+'Cadre output'!T5 | C5: ='Cadre output'!U5 | D5: ='Cadre output'!E5+'Cadre output'!F5 | E5: ='Cadre output'!B5+'Cadre output'!C5+'Cadre output'!D5 | F5: ='Cadre output'!G5+'Cadre output'!H5+'Cadre output'!I5 | G5: ='Cadre output'!J5+'Cadre output'!K5+'Cadre output'!L5+'Cadre output'!M5 | H5: =SUM(B5:G5)
A6: 2031 | B6: ='Cadre output'!N6+'Cadre output'!O6+'Cadre output'!P6+'Cadre output'!Q6+'Cadre output'!R6+'Cadre output'!S6+'Cadre output'!T6 | C6: ='Cadre output'!U6 | D6: ='Cadre output'!E6+'Cadre output'!F6 | E6: ='Cadre output'!B6+'Cadre output'!C6+'Cadre output'!D6 | F6: ='Cadre output'!G6+'Cadre output'!H6+'Cadre output'!I6 | G6: ='Cadre output'!J6+'Cadre output'!K6+'Cadre output'!L6+'Cadre output'!M6 | H6: =SUM(B6:G6)
A7: 2032 | B7: ='Cadre output'!N7+'Cadre output'!O7+'Cadre output'!P7+'Cadre output'!Q7+'Cadre output'!R7+'Cadre output'!S7+'Cadre output'!T7 | C7: ='Cadre output'!U7 | D7: ='Cadre output'!E7+'Cadre output'!F7 | E7: ='Cadre output'!B7+'Cadre output'!C7+'Cadre output'!D7 | F7: ='Cadre output'!G7+'Cadre output'!H7+'Cadre output'!I7 | G7: ='Cadre output'!J7+'Cadre output'!K7+'Cadre output'!L7+'Cadre output'!M7 | H7: =SUM(B7:G7)
A8: 2033 | B8: ='Cadre output'!N8+'Cadre output'!O8+'Cadre output'!P8+'Cadre output'!Q8+'Cadre output'!R8+'Cadre output'!S8+'Cadre output'!T8 | C8: ='Cadre output'!U8 | D8: ='Cadre output'!E8+'Cadre output'!F8 | E8: ='Cadre output'!B8+'Cadre output'!C8+'Cadre output'!D8 | F8: ='Cadre output'!G8+'Cadre output'!H8+'Cadre output'!I8 | G8: ='Cadre output'!J8+'Cadre output'!K8+'Cadre output'!L8+'Cadre output'!M8 | H8: =SUM(B8:G8)
A9: 2034 | B9: ='Cadre output'!N9+'Cadre output'!O9+'Cadre output'!P9+'Cadre output'!Q9+'Cadre output'!R9+'Cadre output'!S9+'Cadre output'!T9 | C9: ='Cadre output'!U9 | D9: ='Cadre output'!E9+'Cadre output'!F9 | E9: ='Cadre output'!B9+'Cadre output'!C9+'Cadre output'!D9 | F9: ='Cadre output'!G9+'Cadre output'!H9+'Cadre output'!I9 | G9: ='Cadre output'!J9+'Cadre output'!K9+'Cadre output'!L9+'Cadre output'!M9 | H9: =SUM(B9:G9)
A10: 2035 | B10: ='Cadre output'!N10+'Cadre output'!O10+'Cadre output'!P10+'Cadre output'!Q10+'Cadre output'!R10+'Cadre output'!S10+'Cadre output'!T10 | C10: ='Cadre output'!U10 | D10: ='Cadre output'!E10+'Cadre output'!F10 | E10: ='Cadre output'!B10+'Cadre output'!C10+'Cadre output'!D10 | F10: ='Cadre output'!G10+'Cadre output'!H10+'Cadre output'!I10 | G10: ='Cadre output'!J10+'Cadre output'!K10+'Cadre output'!L10+'Cadre output'!M10 | H10: =SUM(B10:G10)
A11: 2036 | B11: ='Cadre output'!N11+'Cadre output'!O11+'Cadre output'!P11+'Cadre output'!Q11+'Cadre output'!R11+'Cadre output'!S11+'Cadre output'!T11 | C11: ='Cadre output'!U11 | D11: ='Cadre output'!E11+'Cadre output'!F11 | E11: ='Cadre output'!B11+'Cadre output'!C11+'Cadre output'!D11 | F11: ='Cadre output'!G11+'Cadre output'!H11+'Cadre output'!I11 | G11: ='Cadre output'!J11+'Cadre output'!K11+'Cadre output'!L11+'Cadre output'!M11 | H11: =SUM(B11:G11)
A12: 2037 | B12: ='Cadre output'!N12+'Cadre output'!O12+'Cadre output'!P12+'Cadre output'!Q12+'Cadre output'!R12+'Cadre output'!S12+'Cadre output'!T12 | C12: ='Cadre output'!U12 | D12: ='Cadre output'!E12+'Cadre output'!F12 | E12: ='Cadre output'!B12+'Cadre output'!C12+'Cadre output'!D12 | F12: ='Cadre output'!G12+'Cadre output'!H12+'Cadre output'!I12 | G12: ='Cadre output'!J12+'Cadre output'!K12+'Cadre output'!L12+'Cadre output'!M12 | H12: =SUM(B12:G12)
A13: 2038 | B13: ='Cadre output'!N13+'Cadre output'!O13+'Cadre output'!P13+'Cadre output'!Q13+'Cadre output'!R13+'Cadre output'!S13+'Cadre output'!T13 | C13: ='Cadre output'!U13 | D13: ='Cadre output'!E13+'Cadre output'!F13 | E13: ='Cadre output'!B13+'Cadre output'!C13+'Cadre output'!D13 | F13: ='Cadre output'!G13+'Cadre output'!H13+'Cadre output'!I13 | G13: ='Cadre output'!J13+'Cadre output'!K13+'Cadre output'!L13+'Cadre output'!M13 | H13: =SUM(B13:G13)
... A25: 2050 | B25: ='Cadre output'!N25+'Cadre output'!O25+'Cadre output'!P25+'Cadre output'!Q25+'Cadre output'!R25+'Cadre output'!S25+'Cadre output'!T25 | C25: ='Cadre output'!U25 | D25: ='Cadre output'!E25+'Cadre output'!F25 | E25: ='Cadre output'!B25+'Cadre output'!C25+'Cadre output'!D25 | F25: ='Cadre output'!G25+'Cadre output'!H25+'Cadre output'!I25 | G25: ='Cadre output'!J25+'Cadre output'!K25+'Cadre output'!L25+'Cadre output'!M25 | H25: =SUM(B25:G25)
A27: WHAT THIS SHEET IS. The Cadre output sheet totalled into six groups. Each cell simply adds that group's cadre columns for the same year.
A28: Every cell is a live formula pointing at the Cadre output sheet, so the two sheets can never disagree.
A29: These are annual qualifications, not practising staff, and must not be added to the doctor stock on the Projection sheet.
A30: GROUP MEMBERSHIP. AYUSH: BAMS (Ayurveda), BSMS (Siddha), BUMS (Unani), BNYS (Naturopathy), BHMS (Homoeopathy), MD Siddha, MD Homoeopathy; Allied health: AHS PG (allied); Dental: BDS, MDS; Nursing: BSc Nursing, MSc Nursing, Post Basic BSc Nursing; Pharmacy: B.Pharm, M.Pharm, Pharm.D; Rehabilitation: BPT, MPT, BOT, MOT

Sheet Nursing
A1: Year | B1: BSc Nursing | C1: MSc Nursing | D1: Post Basic BSc Nursing | E1: Total degree level nursing
A2: 2027 | B2: ='Cadre output'!B2 | C2: ='Cadre output'!C2 | D2: ='Cadre output'!D2 | E2: =SUM(B2:D2)
A3: 2028 | B3: ='Cadre output'!B3 | C3: ='Cadre output'!C3 | D3: ='Cadre output'!D3 | E3: =SUM(B3:D3)
A4: 2029 | B4: ='Cadre output'!B4 | C4: ='Cadre output'!C4 | D4: ='Cadre output'!D4 | E4: =SUM(B4:D4)
A5: 2030 | B5: ='Cadre output'!B5 | C5: ='Cadre output'!C5 | D5: ='Cadre output'!D5 | E5: =SUM(B5:D5)
A6: 2031 | B6: ='Cadre output'!B6 | C6: ='Cadre output'!C6 | D6: ='Cadre output'!D6 | E6: =SUM(B6:D6)
A7: 2032 | B7: ='Cadre output'!B7 | C7: ='Cadre output'!C7 | D7: ='Cadre output'!D7 | E7: =SUM(B7:D7)
A8: 2033 | B8: ='Cadre output'!B8 | C8: ='Cadre output'!C8 | D8: ='Cadre output'!D8 | E8: =SUM(B8:D8)
A9: 2034 | B9: ='Cadre output'!B9 | C9: ='Cadre output'!C9 | D9: ='Cadre output'!D9 | E9: =SUM(B9:D9)
A10: 2035 | B10: ='Cadre output'!B10 | C10: ='Cadre output'!C10 | D10: ='Cadre output'!D10 | E10: =SUM(B10:D10)
A11: 2036 | B11: ='Cadre output'!B11 | C11: ='Cadre output'!C11 | D11: ='Cadre output'!D11 | E11: =SUM(B11:D11)
A12: 2037 | B12: ='Cadre output'!B12 | C12: ='Cadre output'!C12 | D12: ='Cadre output'!D12 | E12: =SUM(B12:D12)
A13: 2038 | B13: ='Cadre output'!B13 | C13: ='Cadre output'!C13 | D13: ='Cadre output'!D13 | E13: =SUM(B13:D13)
... A25: 2050 | B25: ='Cadre output'!B25 | C25: ='Cadre output'!C25 | D25: ='Cadre output'!D25 | E25: =SUM(B25:D25)
A27: Degree level nursing only. GNM and ANM are absent from every source file because they sit with the Tamil Nadu Nurses and Midwives
A28: Council rather than the university, so these figures understate total nursing output considerably.
A29: Note the fill rates behind these columns: BSc Nursing fills 97 per cent of its seats, but MSc Nursing 59 per cent and Post Basic 48 per cent.

Sheet Data quality
A1: Cadre | B1: Year excluded | C1: Reported pass-outs | D1: Years retained | E1: Reason
A2: BSc Nursing | B2: 2024 | C2: 710 | D2: 7,315, 8,983, 9,189, 10,311 | E2: Excluded as a partial extract: below half the median of the cadre's own pass-out series.
A3: Post Basic BSc Nursing | B3: 2022 | C3: 98 | D3: 562, 717, 766, 1,339 | E3: Excluded as a partial extract: below half the median of the cadre's own pass-out series.
A4: BDS | B4: 2024 | C4: 162 | D4: 1,446, 1,547, 1,840 | E4: Excluded as a partial extract: below half the median of the cadre's own pass-out series.
A5: B.Pharm | B5: 2024 | C5: 803 | D5: 3,572, 4,087, 4,351, 5,980 | E5: Excluded as a partial extract: below half the median of the cadre's own pass-out series.
A6: M.Pharm | B6: 2022 | C6: 17 | D6: 512, 579, 937, 1,114 | E6: Excluded as a partial extract: below half the median of the cadre's own pass-out series.
A7: BPT | B7: 2024 | C7: 299 | D7: 1,260, 1,388, 1,446, 1,476 | E7: Excluded as a partial extract: below half the median of the cadre's own pass-out series.
A8: MPT | B8: 2022 | C8: 69 | D8: 229, 274, 352, 535 | E8: Excluded as a partial extract: below half the median of the cadre's own pass-out series.
A9: BOT | B9: 2024 | C9: 11 | D9: 134, 149, 154, 155 | E9: Excluded as a partial extract: below half the median of the cadre's own pass-out series.
A10: MOT | B10: 2022 | C10: 3 | D10: 18, 20, 28, 35 | E10: Excluded as a partial extract: below half the median of the cadre's own pass-out series.
A11: BUMS (Unani) | B11: 2024 | C11: 21 | D11: 57, 58, 60 | E11: Excluded as a partial extract: below half the median of the cadre's own pass-out series.
A12: MD Siddha | B12: 2024 | C12: 2 | D12: 143, 146, 148, 150 | E12: Excluded as a partial extract: below half the median of the cadre's own pass-out series.
A13: MD Homoeopathy | B13: 2024 | C13: 1 | D13: 28, 41, 44, 48 | E13: Excluded as a partial extract: below half the median of the cadre's own pass-out series.

Sheet Not covered
A1: Cadre or course | B1: Why it is not projected
A2: GNM nursing | B2: Not present in any source file. Sits with the Tamil Nadu Nurses and Midwives Council, not the university.
A3: ANM nursing | B3: Not present in any source file. Same reason as GNM.
A4: AHS UG (allied health, degree) | B4: Present but internally inconsistent: the sheet reports 10,593 admissions against 3,904 sanctioned seats for 2025, a fill rate of 271 per cent, and pass-outs swing from 80 to 10,716 to 508 across four years. Not usable without clarification from the university.
A5: MD Naturopathy and Yoga, MD Unani | B5: Seat counts present but very small (65 and 11 seats) and pass-out sheets are incomplete. Folded into no projection.
A6: Pharm.D Post Baccalaureate | B6: Only three pass-out years, two of them clearly partial.

Sheet Total output
A1: Year | B1: MBBS (doctors) | C1: PG medical | D1: AYUSH | E1: Allied health | F1: Dental | G1: Nursing | H1: Pharmacy | I1: Rehabilitation | J1: Total qualified output, all cadres
A2: 2027 | B2: =Projection!H18 | C2: =Projection!S18 | D2: ='Cadre by group'!B2 | E2: ='Cadre by group'!C2 | F2: ='Cadre by group'!D2 | G2: ='Cadre by group'!E2 | H2: ='Cadre by group'!F2 | I2: ='Cadre by group'!G2 | J2: =SUM(B2:I2)
A3: 2028 | B3: =Projection!H19 | C3: =Projection!S19 | D3: ='Cadre by group'!B3 | E3: ='Cadre by group'!C3 | F3: ='Cadre by group'!D3 | G3: ='Cadre by group'!E3 | H3: ='Cadre by group'!F3 | I3: ='Cadre by group'!G3 | J3: =SUM(B3:I3)
A4: 2029 | B4: =Projection!H20 | C4: =Projection!S20 | D4: ='Cadre by group'!B4 | E4: ='Cadre by group'!C4 | F4: ='Cadre by group'!D4 | G4: ='Cadre by group'!E4 | H4: ='Cadre by group'!F4 | I4: ='Cadre by group'!G4 | J4: =SUM(B4:I4)
A5: 2030 | B5: =Projection!H21 | C5: =Projection!S21 | D5: ='Cadre by group'!B5 | E5: ='Cadre by group'!C5 | F5: ='Cadre by group'!D5 | G5: ='Cadre by group'!E5 | H5: ='Cadre by group'!F5 | I5: ='Cadre by group'!G5 | J5: =SUM(B5:I5)
A6: 2031 | B6: =Projection!H22 | C6: =Projection!S22 | D6: ='Cadre by group'!B6 | E6: ='Cadre by group'!C6 | F6: ='Cadre by group'!D6 | G6: ='Cadre by group'!E6 | H6: ='Cadre by group'!F6 | I6: ='Cadre by group'!G6 | J6: =SUM(B6:I6)
A7: 2032 | B7: =Projection!H23 | C7: =Projection!S23 | D7: ='Cadre by group'!B7 | E7: ='Cadre by group'!C7 | F7: ='Cadre by group'!D7 | G7: ='Cadre by group'!E7 | H7: ='Cadre by group'!F7 | I7: ='Cadre by group'!G7 | J7: =SUM(B7:I7)
A8: 2033 | B8: =Projection!H24 | C8: =Projection!S24 | D8: ='Cadre by group'!B8 | E8: ='Cadre by group'!C8 | F8: ='Cadre by group'!D8 | G8: ='Cadre by group'!E8 | H8: ='Cadre by group'!F8 | I8: ='Cadre by group'!G8 | J8: =SUM(B8:I8)
A9: 2034 | B9: =Projection!H25 | C9: =Projection!S25 | D9: ='Cadre by group'!B9 | E9: ='Cadre by group'!C9 | F9: ='Cadre by group'!D9 | G9: ='Cadre by group'!E9 | H9: ='Cadre by group'!F9 | I9: ='Cadre by group'!G9 | J9: =SUM(B9:I9)
A10: 2035 | B10: =Projection!H26 | C10: =Projection!S26 | D10: ='Cadre by group'!B10 | E10: ='Cadre by group'!C10 | F10: ='Cadre by group'!D10 | G10: ='Cadre by group'!E10 | H10: ='Cadre by group'!F10 | I10: ='Cadre by group'!G10 | J10: =SUM(B10:I10)
A11: 2036 | B11: =Projection!H27 | C11: =Projection!S27 | D11: ='Cadre by group'!B11 | E11: ='Cadre by group'!C11 | F11: ='Cadre by group'!D11 | G11: ='Cadre by group'!E11 | H11: ='Cadre by group'!F11 | I11: ='Cadre by group'!G11 | J11: =SUM(B11:I11)
A12: 2037 | B12: =Projection!H28 | C12: =Projection!S28 | D12: ='Cadre by group'!B12 | E12: ='Cadre by group'!C12 | F12: ='Cadre by group'!D12 | G12: ='Cadre by group'!E12 | H12: ='Cadre by group'!F12 | I12: ='Cadre by group'!G12 | J12: =SUM(B12:I12)
A13: 2038 | B13: =Projection!H29 | C13: =Projection!S29 | D13: ='Cadre by group'!B13 | E13: ='Cadre by group'!C13 | F13: ='Cadre by group'!D13 | G13: ='Cadre by group'!E13 | H13: ='Cadre by group'!F13 | I13: ='Cadre by group'!G13 | J13: =SUM(B13:I13)
... A25: 2050 | B25: =Projection!H41 | C25: =Projection!S41 | D25: ='Cadre by group'!B25 | E25: ='Cadre by group'!C25 | F25: ='Cadre by group'!D25 | G25: ='Cadre by group'!E25 | H25: ='Cadre by group'!F25 | I25: ='Cadre by group'!G25 | J25: =SUM(B25:I25)
A27: Every column here is ANNUAL QUALIFIED OUTPUT, that is people finishing a course, on a Tamil Nadu seat basis. Every cell is a live formula.
A28: It is NOT a practising workforce count and must not be added to the doctor stock on the Projection sheet.
A29: The MBBS column is domestic output from Tamil Nadu seats only. The register also takes in deemed university, out of state and foreign
A30: medical graduates, which is why entrants on the Projection sheet run at roughly double this column.
A31: A practising stock total across all cadres is not possible from the available data, because only doctors have a register.
A32: Nursing is degree level only. GNM and ANM are absent from every source file, so nursing output is understated here.

Sheet Assumptions
A1: Assumption | B1: Status | C1: Basis, and the arithmetic where there is any | D1: Outstanding action
A2: Deemed overlap, 806 graduates per year from 2031 | B2: DERIVED, arithmetic shown | C2: The Selection Committee and MGRMU private MBBS series agree exactly for 2021-22 and 2022-23, then diverge by 450 seats (2023-24), 550 (2024-25) and 850 (2025-26). The gap is most likely deemed universities entering the Selection Committee sheet. Deemed output already sits inside the external-entrant residual, which was estimated from seat years when the two sources still agreed, so without a correction those graduates would be counted twice. The arithmetic is: 850 seats x 0.998 fill x 0.95 completion = 806 graduates per year. The 6-year MBBS lag makes seat year 2025 register in 2031, which is why the full correction starts then; 2029 and 2030 take the smaller 450 and 550 gaps. Computed live in cell B13 of the Inputs sheet. | D2: None. Arithmetic follows from two observed series.
A3: Private MBBS ceilings: 8,000 / 10,000 / 12,000 seats | B3: EXPERT-JUDGMENT SCENARIO BOUNDS, not derived | C3: These are NOT calculated from faculty norms, bed capacity or the applicant pool. No arithmetic connects those inputs to these three numbers. They are round-number bounds chosen to span a plausible range around the 2025 level of 4,750, and the considerations above are the reasoning for the range being finite rather than the source of the specific values. They are presented as three scenarios precisely because the ceiling is not knowable from the data. What the data does support is that growth is bounded rather than compounding: extrapolating the observed compound rate gives 183,707 seats by 2050, which is not credible. | D3: FOR STATE CONFIRMATION. The State is better placed to say what private expansion it will approve. A derived ceiling would need NMC faculty returns and hospital bed data per college, which we do not hold.
A4: PG seats capped at 70 per cent of MBBS seats | B4: OWN ASSUMPTION, not sourced | C4: There is no citation for 70 per cent. It is our own figure, not taken from the Andhra Pradesh model or any published norm. The reasoning is structural: PG intake cannot indefinitely exceed the MBBS pipeline that feeds it. For scale, the ratio was 56 per cent in 2025-26 (5,534 PG against 9,950 MBBS) and national policy has moved toward parity, so 70 per cent sits between the current position and a 1:1 target. The cap binds only after 2040 in the central case, so it moves the near-term projection very little. | D4: FOR STATE CONFIRMATION. Replace with the State's own PG expansion intent if one exists.
A5: Government seat paths, including policy push | B5: POLICY SCENARIOS, not extrapolations | C5: Government sets these seats, so these are scenarios about decisions. All three are built from the observed college-level distribution: 37 colleges, 5,200 seats, mean 141, with sixteen at 100 seats, sixteen at 150, one at 200 and four at the NMC ceiling of 250. Frozen holds 5,200, a no-action counterfactual. Consolidation reaches 6,000 by 2035, which is the sixteen 100-seat colleges rising to 150. Policy push reaches 9,250 by 2045, which is every college reaching the NMC ceiling of 250 and requires no new college. Ramps are linear and rounded to NMC's 50-seat approval blocks. | D5: FOR STATE CONFIRMATION. The target levels, the years by which they are reached, and whether new colleges are planned in addition to intake increases, all need the State's input. The policy push path in particular is our construction and should be replaced by the State's actual capacity plan.
A6: Age at registration, 24 years | B6: INFERRED, not observed | C6: MBBS entry at 18 plus 5.5 years to qualification. Age is never recorded in the scraped register, only year of registration, so every age in the model is inferred from it. Retirement timing is the output most sensitive to this. See the Age sensitivity sheet: varying the assumption from 22 to 26 moves the 2050 stock by under 3 per cent but moves cumulative retirements to 2050 by about 18 per cent. | D6: Resolvable with data. The NMC detail records carry birth dates; a stratified sample of 5,000 to 8,000 records would replace the assumption with an estimate.
A7: Emigration and out-of-state loss, 1.2 per cent per year, ages 25 to 45 | B7: CALIBRATED, not observed | C7: No direct measure of Tamil Nadu doctor out-migration exists. The rate implies about 22 per cent cumulative loss across the exposed ages. It is the model's most consequential single parameter. | D7: Resolvable with data. The NMC removedStatus field records removals from the register and would allow this to be estimated rather than calibrated.
A8: Revised projected need: growth paths of its three drivers | B8: ASSUMED, FOR STATE CONFIRMATION | C8: The elasticities are published (Liu JX, Goryakin Y, Maeda A, Bruckner T, Scheffler RM. Global Health Workforce Labor Market Projections for 2030. Human Resources for Health. 2017;15:11. doi:10.1186/s12960-017-0187-2. First issued as World Bank Policy Research Working Paper 7790, Washington DC: World Bank; 2016., Table 1): 0.244 to real GDP per capita in the long run, -0.099 to out-of-pocket spending per capita, 0.516 to the population aged 65 and over. What is assumed is the path of the drivers: real GSDP per capita growth of 6.5 per cent in 2026 easing to 4.0 per cent by 2050, out-of-pocket spending growing with GDP (share constant), and the 65+ population growing 3.5 per cent a year. The State's own GSDP forecast and the NCP 2019 age tables should replace these. The line is anchored on the modelled 2025 density, which is how the paper's country fixed effect works. | D8: Moderate. Demand reaches 305,668 by 2050 on these paths; supply is 517,657. A faster economy raises the line, but with an elasticity of 0.244 it would take implausible growth to close the gap.
A9: Population growth beyond 2025, 0.30 per cent a year held constant | B9: OWN CHOICE, RATE FROM NCP | C9: The NCP series is used verbatim to 2025. Its 2021 to 2025 average rate is then held constant to 2050, so the population reaches 83.3 million and the WHO requirement rises with it. The NCP series itself plateaus near 78 million from 2031; that path gives 76.0 million in 2050 and is kept as an alternative in the dashboard. | D9: Moderate. Density in 2050 is 62.2 per 10,000 on this path against 68.1 on the NCP plateau; the surplus finding holds on both.
A10: Completion rate, 95 per cent for medical courses | B10: BENCHMARK, validated | C10: Taken as the NMC benchmark and also used in the Andhra Pradesh model. It is not estimated from Tamil Nadu data directly for MBBS because no admission cohort in the observed window can be matched to its own pass-out year at a 6-year lag. It was validated indirectly on PG, where the match is possible: predicted 2,707 against 2,717 observed. | D10: None outstanding.
A11: Cadre seat growth: frozen, or trend continued to 2035 then held | B11: OWN ASSUMPTION | C11: With four or five annual observations per cadre a fitted ceiling cannot be supported, so two bounding paths are given instead. Holding flat after 2035 reflects that capacity cannot expand indefinitely against a falling state population. | D11: FOR STATE CONFIRMATION alongside the medical seat paths.

Sheet Age sensitivity
A1: Age assumed at registration | B1: Active doctors 2025 | C1: Active doctors 2050 | D1: Retirements in 2050 | E1: Cumulative retirements 2026-2050 | F1: Note
A2: 22 | B2: 155889 | C2: 531587 | D2: 1532 | E2: 25764
A3: 23 | B3: 153624 | C3: 524705 | D3: 1658 | E3: 26669
A4: 24 | B4: 151248 | C4: 517657 | D4: 1692 | E4: 27600 | F4: Central case
A5: 25 | B5: 150548 | C5: 516644 | D5: 1745 | E5: 28898
A6: 26 | B6: 149738 | C6: 515463 | D6: 1978 | E6: 30337
A8: Age is never observed in the register. Only year of registration is recorded, so every age in the model is inferred as 24 plus years elapsed.
A9: Registration at 24 assumes MBBS entry at 18 plus 5.5 years to qualification.
A10: The stock is robust to this assumption and the retirement profile is not. Across the range 22 to 26 the 2050 stock moves by under 3 per cent, while cumulative
A11: retirements to 2050 move by about 18 per cent. Any statement about when Tamil Nadu's retirement wave arrives therefore carries this uncertainty.
A12: The NMC detail records carry birth dates. A stratified sample of 5,000 to 8,000 records would replace this assumption with an estimate.

Sheet Parameters
A1: Module | B1: Parameter | C1: Value | D1: Basis and source
A2: Population | B2: NCP projection 2011-2025 | C2: 72.1M to 77.3M | D2: National Commission on Population, Ministry of Health and Family Welfare. Population Projections for India and States 2011-2036: Report of the Technical Group on Population Projections. New Delhi: Government of India; July 2019. Used verbatim to 2025.
A3: Population | B3: Growth rate beyond 2025 | C3: 0.298%/yr, held constant to 2050 | D3: The NCP series' own 2021 to 2025 rate. Gives 83.3M in 2050. The NCP plateau (76.0M in 2050) is the alternative path in the dashboard.
A4: Seats, government | B4: College-level starting position | C4: 37 colleges, 5,200 seats, mean 141 | D4: MGRMU 2025: sixteen colleges at 100 seats, sixteen at 150, one at 200, four at the NMC ceiling of 250. Tamil Nadu has 37 government medical colleges across 38 districts, so coverage is near-universal and the realistic lever is raising intake at existing colleges rather than building new ones.
A5: Seats, government | B5: Frozen path (Constrained) | C5: 5,200, held flat | D5: A no-action COUNTERFACTUAL, not a forecast. Seats are set by government, so this is the path only if no intake decision is taken anywhere for 25 years.
A6: Seats, government | B6: Consolidation path (Status quo) | C6: 6,000 by 2035 | D6: The sixteen 100-seat colleges rise to 150. The smallest realistic policy step.
A7: Seats, government | B7: Full-capacity path (Policy push) | C7: 9,250 by 2045 | D7: Every one of the 37 colleges reaches the NMC ceiling of 250 seats. Requires no new college at all. Ramps are rounded to NMC's 50-seat approval blocks.
A8: Seats, private | B8: Logistic ceiling K | C8: 8,000 / 10,000 / 12,000 | D8: Scenario range. Ceilings reasoned from NMC faculty norms, clinical-material (bed) requirements, the NEET-qualified applicant pool, and a declining state population.
A9: Seats, private | B9: Fitted growth rate and inflection year | C9: K=8,000: r=0.226, 2023.5; K=10,000: r=0.204, 2025.5; K=12,000: r=0.188, 2027.2 | D9: Least-squares fit in levels to the 2015-16 to 2025-26 Selection Committee series.
A10: Seats, PG | B10: Linear slope | C10: +321.5 seats per year | D10: OLS in levels on the full-basis PG series 2021-2025. Increments are near-constant, so linear rather than CAGR.
A11: Seats, PG | B11: Structural cap | C11: 70% of total MBBS seats | D11: You cannot train more specialists than the MBBS pipeline delivers.
A12: Pipeline | B12: MBBS fill rate | C12: 99.8% | D12: MGRMU seat-count data, sanctioned against admitted, 2021-2025. For 2025, 9,053 admitted against 9,100 approved.
... A24: Need | B24: Doctor share of the norm | C24: 25%, doctor to nurse 1 to 3 | D24: WHO (2016). Gives 11.125 doctors per 10,000 population.

Sheet Methodology
A1: Section | B1: Text
A2: Framework | B2: A stock-and-flow supply model with an explicit education pipeline, following the WHO / World Bank Health Labour Market Framework as operationalised in Liu JX, Goryakin Y, Maeda A, Bruckner T, Scheffler RM. Global Health Workforce Labor Market Projections for 2030. Human Resources for Health. 2017;15:11. doi:10.1186/s12960-017-0187-2. First issued as World Bank Policy Research Working Paper 7790, Washington DC: World Bank; 2016. and in World Health Organization. Health Labour Market Analysis Guidebook. Geneva: WHO; 2021. The same three-lens structure, Supply, Need and Demand, used in the Centre's Andhra Pradesh projection. This round builds the Supply lens for Tamil Nadu to 2050, sets it against the WHO need floor, and adds the revised projected need line, which is the demand side of the same paper.
A3: Why not CAGR | B3: Growth forms were tested, not assumed. Comparing a levels-linear fit against a log-linear (CAGR) fit on a common scale, RMSE in seats, since a log model's R-squared is not comparable with a levels model's: private MBBS seats fit exponential over the full eleven years (RMSE 163 against 237) but linear over the recent window, 2019-20 onward (RMSE 83 against 150). The exponential advantage comes entirely from the small 2015-16 base. Increments have been flatly additive at about 460 seats per year since 2019-20.
A4: Why not CAGR, continued | B4: Government MBBS is not a growth curve at all: five of ten historical years show zero change, three are large jumps, and the last four years total +25 seats. It is modelled as a step process. Extrapolating CAGR to 2050 would give 183,707 private MBBS seats against about 10,000 on a bounded fit, an eighteen-fold error. CAGR is used in this work only as a descriptive statistic for history, never as the forecast engine.
A5: Why the logistic | B5: A logistic curve is approximately exponential in its early phase and approximately linear through its middle phase. Fitting private MBBS with a ceiling of 10,000 puts the inflection at 2025.5, so Tamil Nadu's private capacity is passing through its linear phase now. That is why the recent window reads linear while the full series reads exponential. Both are the same curve at different points.
A6: Module 1, population | B6: NCP / MoHFW official projections used verbatim to 2025. From 2026 the population grows at the NCP series' own 2021 to 2025 rate, 0.298% per year, held constant. Result: 77.32 million in 2025, 79.89 million in 2036, 83.29 million in 2050. The NCP plateau near 78 million is kept as an alternative path in the dashboard.
A7: Module 6b, revised projected need | B7: A need line revised for the state's own economy, on the demand model of Liu et al. 2017: ln(physicians per 1,000) = -9.882 + 0.231 ln GDPpc(t-1) + 0.531 ln GDPpc(t-4) - 0.518 ln GDPpc(t-5) - 0.099 ln OOPpc(t-2) + 0.516 ln Pop65(t-3) + country effect, estimated by GLM with country fixed effects on 165 countries, 1990 to 2013. The country effect pins the level, so the line is anchored on Tamil Nadu's modelled 2025 density and moved by the three drivers, whose growth paths are assumptions marked for State confirmation. Result: 151,248 in 2025, 233,187 in 2040, 305,668 in 2050. Supply exceeds it throughout; the gap is 211,989 doctors in 2050.
A8: Module 2, seats | B8: Government and private modelled separately because they are on different trajectories. Government is a step and scenario process. Private follows bounded logistic growth fitted in levels at three ceilings. PG seats grow linearly, capped at 70% of total MBBS seats.
A9: Module 3, pipeline | B9: Seats to admissions via the fill rate, admissions to graduates via the completion rate, graduates to the register with a lag. Fill rates are estimated directly from MGRMU sanctioned-against-admitted data: 99.8% for MBBS, 97.8% for PG. Completion is 95%. The MBBS lag is six years, being 4.5 academic years plus a twelve-month internship; the PG lag is three years.
A10: Module 4, external entrants | B10: The residual between observed registrations and modelled domestic output, decomposed into foreign medical graduates, which are observed and projected linearly to a ceiling of 3,000, and deemed-university plus out-of-state entrants, held flat at the observed mean because the five observations show no trend.
A11: Module 5, stock and flow | B11: Register cohorts are rolled forward from 1927, with age inferred from registration year at an assumed age of 24. Three separate outflows apply: age-specific mortality; emigration and out-of-state loss at 1.2% per year across ages 25 to 45; and a retirement hazard reducing participation from age 60.
A12: Module 6, specialists | B12: Specialists are tracked as a transition within the stock, never as an addition to it. An MD or MS entrant is an already-registered MBBS doctor, so adding PG output to MBBS output would double-count every specialist.
... A25: Limitation, other | B25: Population beyond 2025 is our own extension, not an official projection. The model is state-level only, with no district, urban-rural, or public-private employment split. Superspecialty (DM and M.Ch) and DNB are folded into the PG account, since only one year of seat data exists for each.

Sheet Provenance
A1: Class | B1: Figure | C1: Value | D1: Source, or how we computed it
A2: TAKEN FROM DATA | B2: MBBS seats, government and self-financing, 2015-16 to 2025-26 | C2: 2,655 to 5,200 and 1,010 to 4,750 | D2: Selection Committee, UG MBBS BDS Data Sheet.xlsx, sheet UG MBBS SS
A3: TAKEN FROM DATA | B3: Government college seat distribution 2025 | C3: 37 colleges: 16 at 100, 16 at 150, 1 at 200, 4 at 250 | D3: MGRMU SEAT COUNT STAT 15052026.xlsx, sheet MBBS
A4: TAKEN FROM DATA | B4: PG seats 2025-26, full basis | C4: 5,534 | D4: Selection Committee MD Seats (3,629) plus MS Seats (1,905)
A5: TAKEN FROM DATA | B5: TNMC MBBS registrations 2020-2025 | C5: 8,409 / 8,058 / 10,367 / 9,370 / 9,722 / 10,839 | D5: TNMC Registrations 2020 to 2025.xlsx, sheet MBBS TNMC
A6: TAKEN FROM DATA | B6: TNMC foreign medical graduate registrations | C6: 640 / 1,268 / 1,287 / 1,622 / 1,427 / 1,606 | D6: Same workbook and sheet
A7: TAKEN FROM DATA | B7: TNMC broad-speciality PG registrations | C7: 2,702 / 4,210 / 5,632 / 5,279 / 2,917 / 8,069 | D7: Same workbook, sheets MD, MS, DNB MedPG, DNB Surg PG
A8: TAKEN FROM DATA | B8: Seats, admissions and pass-outs, 20 other cadres | C8: 2021 to 2025 | D8: MGRMU SEAT COUNT STAT and passout COUNT STAT, 26 sheets each
A9: ESTIMATED BY US | B9: MBBS fill rate | C9: 0.998 | D9: Admissions over sanctioned seats, pooled 2021-2025. 2025: 9,053 of 9,100
A10: ESTIMATED BY US | B10: PG fill rate | C10: 0.978 | D10: Same method, MGRMU PG MEDICAL sheet
A11: ESTIMATED BY US | B11: Fill rates, 20 other cadres | C11: 0.48 to 0.97 | D11: Same method per cadre. Post Basic Nursing 0.48, BSc Nursing 0.97
A12: ESTIMATED BY US | B12: Completion rates, 11 of 20 cadres | C12: 0.76 to 0.99 | D12: Pass-outs over the admissions of the cohort one course length earlier
... A41: SCRAPED BY US | B41: Full TNMC register | C41: 193,264 doctors, 1927 to 2025 | D41: NMC Indian Medical Register, scraped via run_all.py, endpoint nmc.org.in/MCIRest/open/getPaginatedData, state council id 21
A43: Roughly 60 per cent of the figures come straight from the supplied files or are computed from them. About 25 per cent are external published sources, almost all of that the population series and the WHO norm.
A44: About 15 per cent are our own assumptions. Five of those matter: the private seat ceilings, the PG cap, the government seat targets, the emigration rate and age at registration.
A45: The first three need the State's confirmation. The last two need data that exists but we do not hold: the NMC detail records carry birth dates and removal status.
A46: Data altered or excluded is on the Data quality sheet. Cadres not projected are on the Not covered sheet. Neither was dropped silently.

Sheet Data Sources
A1: Category | B1: Source | C1: Publisher | D1: Coverage | E1: Used for | F1: Location or link | G1: Status
A2: Primary data | B2: UG MBBS / BDS Data Sheet | C2: TN Medical Selection Committee | D2: 2015-16 to 2025-26 | E2: MBBS seats, Government against Self-financing. The seat module backbone. | F2: new data/Selection committee/UG MBBS BDS Data Sheet.xlsx | G2: User-provided
A3: Primary data | B3: MD Seats 10 years | C3: TN Medical Selection Committee | D3: 2016-17 to 2025-26 | E3: MD seats by college, with a four-way Government, Central, Private-TNMMU and Private-Deemed split in recent years | F3: new data/Selection committee/MD Seats 10 years.xlsx | G3: User-provided
A4: Primary data | B4: MS Seats 10 years | C4: TN Medical Selection Committee | D4: 2016-17 to 2025-26 | E4: MS seats by college, same structure | F4: new data/Selection committee/MS Seats 10 years.xlsx | G4: User-provided
A5: Primary data | B5: PG Diploma seats in 10 years | C5: TN Medical Selection Committee | D5: 2016-17 to 2025-26 | E5: PG Diploma seats, a collapsing stream from 396 to 25 | F5: new data/Selection committee/PG Diploma seats in 10 years.xlsx | G5: User-provided
A6: Primary data | B6: Super Speciality Seat Matrix, AIQ and SQ | C6: TN Medical Selection Committee | D6: 2025-26 only | E6: DM and M.Ch seats, 422 in total across 13 government colleges | F6: new data/Selection committee/SUPER SPECIALITY SEAT MATRIX 2025-26AIQ_SQ.xlsx | G6: User-provided
A7: Primary data | B7: DNB Seat Matrix | C7: TN Medical Selection Committee | D7: 2025-26 only | E7: DNB seats at government district hospitals, about 40 | F7: new data/Selection committee/DNB SEAT MATRIX 2025-2026.xlsx | G7: User-provided
A8: Primary data | B8: Seat Count Stat, 15.05.2026 | C8: TN Dr. M.G.R. Medical University | D8: 2021-2025, 27 courses | E8: Sanctioned seats and actual admissions by institution. Gives the fill rate directly. | F8: new data/TN MGRMU/SEAT COUNT STAT 15052026.xlsx | G8: User-provided
A9: Primary data | B9: Passout Count Stat, 15.05.2026 | C9: TN Dr. M.G.R. Medical University | D9: 2021-2025, 26 courses | E9: Actual graduates by institution and category. Gives the completion rate. | F9: new data/TN MGRMU/passout COUNT STAT 15052026.xlsx | G9: User-provided
A10: Primary data | B10: Consolidated all-course faculty, 18.6.2025 | C10: TN Dr. M.G.R. Medical University | D10: 2025 | E10: Faculty norms per course. Informs the teaching-capacity ceiling. | F10: new data/TN MGRMU/consolidated all course 18.6.2025.xlsx | G10: User-provided
A11: Primary data | B11: TNMC Registrations 2020 to 2025 | C11: Tamil Nadu Medical Council | D11: 2020-2025 | E11: Registrations by course, year and sex: MBBS, FMG, MD, MS, DM, M.Ch, DNB and PG Diploma | F11: new data/Medical Council/TNMC Registrations 2020 to 2025.xlsx | G11: User-provided
A12: Primary data | B12: Prospectuses: MBBS, DNB, Superspeciality | C12: TN Selection Committee / Govt. of Tamil Nadu | D12: 2024-25 and 2025-26 | E12: Course durations, internship rules, eligibility and service-candidate quotas | F12: new data/prospectus/*.pdf | G12: User-provided
... A35: Internal | B35: TN_Projection_shan.xlsx and Overleaf deck | C35: CMHS, IIM Ahmedabad | D35: 2026 | E35: The earlier Tamil Nadu Need-lens round, WHO and IPHS facility norms to 2036 | F35: TN_Projection_shan.xlsx, overleaf/ | G35: Internal
